<?xml version="1.0" encoding="windows-1252"?>
<XMI xmi.version="1.1" xmlns:UML="omg.org/UML1.3">
	<XMI.header>
		<XMI.documentation>
			<XMI.exporter>Enterprise Architect</XMI.exporter>
			<XMI.exporterVersion>2.5</XMI.exporterVersion>
		</XMI.documentation>
	</XMI.header>
	<XMI.content>
		<UML:Model name="EA Model" xmi.id="MX_EAID_45020593_84CC_4e21_BA1B_E523CF0BBA0A">
			<UML:Namespace.ownedElement>
				<UML:Class name="EARootClass" xmi.id="EAID_11111111_5487_4080_A7F4_41526CB0AA00" isRoot="true" isLeaf="false" isAbstract="false"/>
				<UML:Package name="HY_HydrometricNetwork" xmi.id="EAPK_45020593_84CC_4e21_BA1B_E523CF0BBA0A" isRoot="false" isLeaf="false" isAbstract="false" visibility="public">
					<UML:ModelElement.stereotype>
						<UML:Stereotype xmi.idref="EAID_F2B96478_2A26_4273_A9FA_BE8F2F80BCFC"/>
					</UML:ModelElement.stereotype>
					<UML:ModelElement.taggedValue>
						<UML:TaggedValue tag="documentation" value="The Hydrometric Network application schema (Figure 45) defines a logical model to take into account a network of hydrometric stations as a specific realization of the catchment in the perspective of hydrologic observation, without the detail of an observation strategy.&#xA;&#xA;The Hydrometric Network model specifies the concepts defined in the Hydro Feature core model.. The general concept is that of a network of logically connected hydrometric stations realizing as a whole the catchment. This enables contextually related information models to relate monitoring stations and observing posts to hydrologic features, as is often required for environmental reporting or when interpreting, analyzing and processing observation results. "/>
						<UML:TaggedValue tag="parent" value="EAPK_C51176F0_6646_4173_82AE_59E0DCC95B06"/>
						<UML:TaggedValue tag="ea_package_id" value="2057"/>
						<UML:TaggedValue tag="created" value="2010-09-13 00:00:00"/>
						<UML:TaggedValue tag="modified" value="2015-09-29 13:20:27"/>
						<UML:TaggedValue tag="iscontrolled" value="TRUE"/>
						<UML:TaggedValue tag="xmlpath" value="HY_HydrometricNetwork.xml"/>
						<UML:TaggedValue tag="lastloaddate" value="2017-06-12 11:55:34"/>
						<UML:TaggedValue tag="lastsavedate" value="2010-10-28 09:25:01"/>
						<UML:TaggedValue tag="version" value="0.0.2"/>
						<UML:TaggedValue tag="isprotected" value="FALSE"/>
						<UML:TaggedValue tag="usedtd" value="FALSE"/>
						<UML:TaggedValue tag="xmiver" value="Enterprise Architect XMI/UML 1.3"/>
						<UML:TaggedValue tag="logxml" value="FALSE"/>
						<UML:TaggedValue tag="tpos" value="9"/>
						<UML:TaggedValue tag="packageFlags" value="Recurse=0;VCCFG=HY_Features;CRC=0;"/>
						<UML:TaggedValue tag="batchsave" value="0"/>
						<UML:TaggedValue tag="batchload" value="0"/>
						<UML:TaggedValue tag="phase" value="1.0"/>
						<UML:TaggedValue tag="status" value="Proposed"/>
						<UML:TaggedValue tag="complexity" value="1"/>
						<UML:TaggedValue tag="stereotype" value="Application Schema"/>
						<UML:TaggedValue tag="ea_stype" value="Public"/>
						<UML:TaggedValue tag="tpos" value="9"/>
						<UML:TaggedValue tag="gentype" value="Java"/>
					</UML:ModelElement.taggedValue>
					<UML:Namespace.ownedElement>
						<UML:Class name="HY_HydrometricNetwork" xmi.id="EAID_5D9E5E19_3F78_4eb2_94E3_74D083F92886" visibility="public" namespace="EAPK_45020593_84CC_4e21_BA1B_E523CF0BBA0A" isRoot="false" isLeaf="false" isAbstract="false" isActive="false">
							<UML:ModelElement.stereotype>
								<UML:Stereotype name="FeatureType"/>
							</UML:ModelElement.stereotype>
							<UML:ModelElement.taggedValue>
								<UML:TaggedValue tag="documentation" value="The HY_HydrometricNetwork feature type specializes the HY_HydroNetwork realization specifically as an aggregate of hydrometric features. &#xA;&#xA;HY_HydrometricNetwork has a &lt;i&gt;networkStation &lt;/i&gt;association&lt;i&gt;, and &lt;/i&gt;inherits through generalization the &lt;i&gt;shape&lt;/i&gt; attribute, the &lt;i&gt;realizedCatchment&lt;/i&gt;, &lt;i&gt;flowpath,&lt;/i&gt; &lt;i&gt;catchmentDivide&lt;/i&gt; and &lt;i&gt;catchmentArea&lt;/i&gt; associations. "/>
								<UML:TaggedValue tag="isSpecification" value="false"/>
								<UML:TaggedValue tag="ea_stype" value="Class"/>
								<UML:TaggedValue tag="ea_ntype" value="0"/>
								<UML:TaggedValue tag="version" value="1.0"/>
								<UML:TaggedValue tag="package" value="EAPK_45020593_84CC_4e21_BA1B_E523CF0BBA0A"/>
								<UML:TaggedValue tag="date_created" value="2009-02-13 15:03:47"/>
								<UML:TaggedValue tag="date_modified" value="2017-06-12 12:00:32"/>
								<UML:TaggedValue tag="gentype" value="Java"/>
								<UML:TaggedValue tag="tagged" value="0"/>
								<UML:TaggedValue tag="package_name" value="HY_HydrometricNetwork"/>
								<UML:TaggedValue tag="phase" value="1.0"/>
								<UML:TaggedValue tag="complexity" value="1"/>
								<UML:TaggedValue tag="status" value="Proposed"/>
								<UML:TaggedValue tag="stereotype" value="FeatureType"/>
								<UML:TaggedValue tag="tpos" value="2"/>
								<UML:TaggedValue tag="ea_localid" value="15738"/>
								<UML:TaggedValue tag="ea_eleType" value="element"/>
								<UML:TaggedValue tag="style" value="BackColor=-1;BorderColor=-1;BorderWidth=-1;FontColor=-1;VSwimLanes=1;HSwimLanes=1;BorderStyle=0;"/>
								<UML:TaggedValue tag="$ea_xref_property" value="$XREFPROP=$XID={D23C0BD3-DA5F-4add-9218-085A7ECD34DC}$XID;$NAM=CustomProperties$NAM;$TYP=element property$TYP;$VIS=Public$VIS;$DES=@PROP=@NAME=isActive@ENDNAME;@TYPE=Boolean@ENDTYPE;@VALU=@ENDVALU;@PRMT=@ENDPRMT;@ENDPROP;$DES;$CLT={5D9E5E19-3F78-4eb2-94E3-74D083F92886}$CLT;$ENDXREF;$XREFPROP=$XID={5152BBB0-AF36-4bc4-8123-16562D2372EF}$XID;$NAM=Stereotypes$NAM;$TYP=element property$TYP;$VIS=Public$VIS;$PAR=0$PAR;$DES=@STEREO;Name=FeatureType;GUID={0A528C27-E4FC-4f99-A077-A60A992F072C};@ENDSTEREO;$DES;$CLT={5D9E5E19-3F78-4eb2-94E3-74D083F92886}$CLT;$SUP=&lt;none&gt;$SUP;$ENDXREF;"/>
							</UML:ModelElement.taggedValue>
						</UML:Class>
						<UML:Association xmi.id="EAID_6E676113_264B_403d_AD04_3C48B5DF0C23" visibility="public" isRoot="false" isLeaf="false" isAbstract="false">
							<UML:ModelElement.taggedValue>
								<UML:TaggedValue tag="documentation" value="hydrometric network of one or more hydrometric stations."/>
								<UML:TaggedValue tag="style" value="1"/>
								<UML:TaggedValue tag="ea_type" value="Aggregation"/>
								<UML:TaggedValue tag="direction" value="Destination -&gt; Source"/>
								<UML:TaggedValue tag="linemode" value="1"/>
								<UML:TaggedValue tag="linecolor" value="-1"/>
								<UML:TaggedValue tag="linewidth" value="0"/>
								<UML:TaggedValue tag="seqno" value="0"/>
								<UML:TaggedValue tag="subtype" value="Weak"/>
								<UML:TaggedValue tag="headStyle" value="0"/>
								<UML:TaggedValue tag="lineStyle" value="0"/>
								<UML:TaggedValue tag="ea_localid" value="23511"/>
								<UML:TaggedValue tag="ea_sourceName" value="HY_HydrometricFeature"/>
								<UML:TaggedValue tag="ea_targetName" value="HY_HydrometricNetwork"/>
								<UML:TaggedValue tag="ea_sourceType" value="Class"/>
								<UML:TaggedValue tag="ea_targetType" value="Class"/>
								<UML:TaggedValue tag="ea_sourceID" value="15739"/>
								<UML:TaggedValue tag="ea_targetID" value="15738"/>
								<UML:TaggedValue tag="$ea_src_xref_property" value="$XREFPROP=$XID={24C5E704-6D69-443f-935C-C148D3BB01B7}$XID;$NAM=CustomProperties$NAM;$TYP=connectorSrcEnd property$TYP;$VIS=Public$VIS;$PAR=0$PAR;$DES=@PROP=@NAME=isComposite@ENDNAME;@TYPE=Boolean@ENDTYPE;@VALU=@ENDVALU;@PRMT=@ENDPRMT;@ENDPROP;@PROP=@NAME=isDerivedUnion@ENDNAME;@TYPE=Boolean@ENDTYPE;@VALU=false@ENDVALU;@PRMT=@ENDPRMT;@ENDPROP;@PROP=@NAME=default@ENDNAME;@TYPE=String@ENDTYPE;@VALU=@ENDVALU;@PRMT=@ENDPRMT;@ENDPROP;@PROP=@NAME=isReadOnly@ENDNAME;@TYPE=Boolean@ENDTYPE;@VALU=false@ENDVALU;@PRMT=@ENDPRMT;@ENDPROP;@PROP=@NAME=isDerived@ENDNAME;@TYPE=Boolean@ENDTYPE;@VALU=false@ENDVALU;@PRMT=@ENDPRMT;@ENDPROP;@PROP=@NAME=aggregation@ENDNAME;@TYPE=AggregationKind@ENDTYPE;@VALU=none@ENDVALU;@PRMT=@ENDPRMT;@ENDPROP;$DES;$CLT={6E676113-264B-403d-AD04-3C48B5DF0C23}$CLT;$SUP=&lt;none&gt;$SUP;$ENDXREF;"/>
								<UML:TaggedValue tag="$ea_dst_xref_property" value="$XREFPROP=$XID={E5DF992E-E576-4e57-A15E-49C12CE08DAC}$XID;$NAM=CustomProperties$NAM;$TYP=connectorDestEnd property$TYP;$VIS=Public$VIS;$PAR=0$PAR;$DES=@PROP=@NAME=isComposite@ENDNAME;@TYPE=Boolean@ENDTYPE;@VALU=@ENDVALU;@PRMT=@ENDPRMT;@ENDPROP;@PROP=@NAME=isDerivedUnion@ENDNAME;@TYPE=Boolean@ENDTYPE;@VALU=false@ENDVALU;@PRMT=@ENDPRMT;@ENDPROP;@PROP=@NAME=default@ENDNAME;@TYPE=String@ENDTYPE;@VALU=@ENDVALU;@PRMT=@ENDPRMT;@ENDPROP;@PROP=@NAME=isReadOnly@ENDNAME;@TYPE=Boolean@ENDTYPE;@VALU=false@ENDVALU;@PRMT=@ENDPRMT;@ENDPROP;@PROP=@NAME=isDerived@ENDNAME;@TYPE=Boolean@ENDTYPE;@VALU=false@ENDVALU;@PRMT=@ENDPRMT;@ENDPROP;@PROP=@NAME=aggregation@ENDNAME;@TYPE=AggregationKind@ENDTYPE;@VALU=none@ENDVALU;@PRMT=@ENDPRMT;@ENDPROP;$DES;$CLT={6E676113-264B-403d-AD04-3C48B5DF0C23}$CLT;$SUP=&lt;none&gt;$SUP;$ENDXREF;"/>
								<UML:TaggedValue tag="virtualInheritance" value="0"/>
								<UML:TaggedValue tag="lb" value="0..*"/>
								<UML:TaggedValue tag="lt" value="+networkStation"/>
								<UML:TaggedValue tag="rb" value="1"/>
								<UML:TaggedValue tag="rt" value="+hydrometricNetwork"/>
							</UML:ModelElement.taggedValue>
							<UML:Association.connection>
								<UML:AssociationEnd visibility="public" multiplicity="0..*" name="networkStation" aggregation="none" isOrdered="false" targetScope="instance" changeable="none" isNavigable="true" type="EAID_BB084F13_AED3_4c9d_9E8F_2C46B9CBC703">
									<UML:ModelElement.taggedValue>
										<UML:TaggedValue tag="description" value="hydrometric feature which realizes the catchment either separately, or as part of the hydrometric network."/>
										<UML:TaggedValue tag="containment" value="Unspecified"/>
										<UML:TaggedValue tag="sourcestyle" value="Union=0;Derived=0;AllowDuplicates=0;Owned=0;Navigable=Navigable;"/>
										<UML:TaggedValue tag="ea_end" value="source"/>
									</UML:ModelElement.taggedValue>
								</UML:AssociationEnd>
								<UML:AssociationEnd visibility="public" multiplicity="1" name="hydrometricNetwork" aggregation="shared" isOrdered="false" targetScope="instance" changeable="none" isNavigable="false" type="EAID_5D9E5E19_3F78_4eb2_94E3_74D083F92886">
									<UML:ModelElement.taggedValue>
										<UML:TaggedValue tag="description" value="hydrometric network the hydrometric feature  is part of."/>
										<UML:TaggedValue tag="containment" value="Unspecified"/>
										<UML:TaggedValue tag="deststyle" value="Union=0;Derived=0;AllowDuplicates=0;Owned=0;Navigable=Non-Navigable;"/>
										<UML:TaggedValue tag="ea_end" value="target"/>
									</UML:ModelElement.taggedValue>
								</UML:AssociationEnd>
							</UML:Association.connection>
						</UML:Association>
						<UML:Generalization subtype="EAID_5D9E5E19_3F78_4eb2_94E3_74D083F92886" supertype="EAID_50BFCF9E_F639_4b92_999F_99D1B94B7A45" xmi.id="EAID_914F43A7_1DA4_411f_9CEA_E5A9A3C8AA82" visibility="public">
							<UML:ModelElement.taggedValue>
								<UML:TaggedValue tag="style" value="1"/>
								<UML:TaggedValue tag="ea_type" value="Generalization"/>
								<UML:TaggedValue tag="direction" value="Source -&gt; Destination"/>
								<UML:TaggedValue tag="linemode" value="1"/>
								<UML:TaggedValue tag="linecolor" value="-1"/>
								<UML:TaggedValue tag="linewidth" value="0"/>
								<UML:TaggedValue tag="seqno" value="0"/>
								<UML:TaggedValue tag="headStyle" value="0"/>
								<UML:TaggedValue tag="lineStyle" value="0"/>
								<UML:TaggedValue tag="ea_localid" value="23510"/>
								<UML:TaggedValue tag="ea_sourceName" value="HY_HydrometricNetwork"/>
								<UML:TaggedValue tag="ea_targetName" value="HY_HydroNetwork"/>
								<UML:TaggedValue tag="ea_sourceType" value="Class"/>
								<UML:TaggedValue tag="ea_targetType" value="Class"/>
								<UML:TaggedValue tag="ea_sourceID" value="15738"/>
								<UML:TaggedValue tag="ea_targetID" value="15697"/>
								<UML:TaggedValue tag="src_visibility" value="Public"/>
								<UML:TaggedValue tag="src_aggregation" value="0"/>
								<UML:TaggedValue tag="src_isOrdered" value="false"/>
								<UML:TaggedValue tag="src_targetScope" value="instance"/>
								<UML:TaggedValue tag="src_changeable" value="none"/>
								<UML:TaggedValue tag="src_isNavigable" value="false"/>
								<UML:TaggedValue tag="src_containment" value="Unspecified"/>
								<UML:TaggedValue tag="src_style" value="Union=0;Derived=0;AllowDuplicates=0;"/>
								<UML:TaggedValue tag="dst_visibility" value="Public"/>
								<UML:TaggedValue tag="dst_aggregation" value="0"/>
								<UML:TaggedValue tag="dst_isOrdered" value="false"/>
								<UML:TaggedValue tag="dst_targetScope" value="instance"/>
								<UML:TaggedValue tag="dst_changeable" value="none"/>
								<UML:TaggedValue tag="dst_isNavigable" value="true"/>
								<UML:TaggedValue tag="dst_containment" value="Unspecified"/>
								<UML:TaggedValue tag="dst_style" value="Union=0;Derived=0;AllowDuplicates=0;"/>
								<UML:TaggedValue tag="virtualInheritance" value="0"/>
							</UML:ModelElement.taggedValue>
						</UML:Generalization>
						<UML:Class name="HY_HydrometricFeature" xmi.id="EAID_BB084F13_AED3_4c9d_9E8F_2C46B9CBC703" visibility="public" namespace="EAPK_45020593_84CC_4e21_BA1B_E523CF0BBA0A" isRoot="false" isLeaf="false" isAbstract="false" isActive="false">
							<UML:ModelElement.stereotype>
								<UML:Stereotype name="FeatureType"/>
							</UML:ModelElement.stereotype>
							<UML:ModelElement.taggedValue>
								<UML:TaggedValue tag="documentation" value="The HY_HydrometricFeature feature type provides a concept of a monitoring station at which data on water are obtained that realizes the catchment either separately or as part of the hydrometric network (Figure 45). &#xA;&#xA;HY_HydrometricFeature has associations for the &lt;i&gt;hydrometricNetwork&lt;/i&gt; in which it participates, and a &lt;i&gt;positionOnRiver&lt;/i&gt;. An &lt;i&gt;outlet-at-station&lt;/i&gt; constraint emphasizes the recognition of a monitoring station as outlet of the catchment that is realized by the hydrometric network."/>
								<UML:TaggedValue tag="isSpecification" value="false"/>
								<UML:TaggedValue tag="ea_stype" value="Class"/>
								<UML:TaggedValue tag="ea_ntype" value="0"/>
								<UML:TaggedValue tag="version" value="1.0"/>
								<UML:TaggedValue tag="package" value="EAPK_45020593_84CC_4e21_BA1B_E523CF0BBA0A"/>
								<UML:TaggedValue tag="date_created" value="2010-09-14 11:43:55"/>
								<UML:TaggedValue tag="date_modified" value="2017-06-12 12:02:51"/>
								<UML:TaggedValue tag="gentype" value="Java"/>
								<UML:TaggedValue tag="tagged" value="0"/>
								<UML:TaggedValue tag="package_name" value="HY_HydrometricNetwork"/>
								<UML:TaggedValue tag="phase" value="1.0"/>
								<UML:TaggedValue tag="complexity" value="1"/>
								<UML:TaggedValue tag="status" value="Proposed"/>
								<UML:TaggedValue tag="stereotype" value="FeatureType"/>
								<UML:TaggedValue tag="tpos" value="1"/>
								<UML:TaggedValue tag="ea_localid" value="15739"/>
								<UML:TaggedValue tag="ea_eleType" value="element"/>
								<UML:TaggedValue tag="style" value="BackColor=-1;BorderColor=-1;BorderWidth=-1;FontColor=-1;VSwimLanes=1;HSwimLanes=1;BorderStyle=0;"/>
								<UML:TaggedValue tag="$ea_xref_property" value="$XREFPROP=$XID={AA4C2404-8AA6-47b1-8176-AF3EE843AF3B}$XID;$NAM=CustomProperties$NAM;$TYP=element property$TYP;$VIS=Public$VIS;$PAR=0$PAR;$DES=@PROP=@NAME=isActive@ENDNAME;@TYPE=Boolean@ENDTYPE;@VALU=@ENDVALU;@PRMT=@ENDPRMT;@ENDPROP;$DES;$CLT={BB084F13-AED3-4c9d-9E8F-2C46B9CBC703}$CLT;$SUP=&lt;none&gt;$SUP;$ENDXREF;$XREFPROP=$XID={D6C3472C-2C42-4e0b-A527-961F3480C060}$XID;$NAM=Stereotypes$NAM;$TYP=element property$TYP;$VIS=Public$VIS;$PAR=0$PAR;$DES=@STEREO;Name=FeatureType;GUID={0A528C27-E4FC-4f99-A077-A60A992F072C};@ENDSTEREO;$DES;$CLT={BB084F13-AED3-4c9d-9E8F-2C46B9CBC703}$CLT;$SUP=&lt;none&gt;$SUP;$ENDXREF;"/>
							</UML:ModelElement.taggedValue>
							<UML:ModelElement.constraint>
								<UML:Constraint name="outlet-at-station">
									<UML:ModelElement.taggedValue>
										<UML:TaggedValue tag="description" value="EXISTS positionOnRiver.realizedNexus, hydrometricNewtwork.realizedCatchment.outflow  is of type HY_HydroLocation,&#xA;&#xA;defines that a monitoring station should be recognized as the outflow of the contributing catchment realized by the hydrometric network the station is part of."/>
										<UML:TaggedValue tag="type" value="Invariant"/>
										<UML:TaggedValue tag="weight" value="0.00"/>
										<UML:TaggedValue tag="status" value="Approved"/>
									</UML:ModelElement.taggedValue>
								</UML:Constraint>
							</UML:ModelElement.constraint>
						</UML:Class>
						<UML:Association xmi.id="EAID_7E04BB82_EFD5_4457_85B3_6BD3A67B53C8" visibility="public" isRoot="false" isLeaf="false" isAbstract="false">
							<UML:ModelElement.taggedValue>
								<UML:TaggedValue tag="documentation" value="hydrometric feature used as reference location."/>
								<UML:TaggedValue tag="style" value="1"/>
								<UML:TaggedValue tag="ea_type" value="Association"/>
								<UML:TaggedValue tag="direction" value="Source -&gt; Destination"/>
								<UML:TaggedValue tag="linemode" value="1"/>
								<UML:TaggedValue tag="linecolor" value="-1"/>
								<UML:TaggedValue tag="linewidth" value="0"/>
								<UML:TaggedValue tag="seqno" value="0"/>
								<UML:TaggedValue tag="headStyle" value="0"/>
								<UML:TaggedValue tag="lineStyle" value="0"/>
								<UML:TaggedValue tag="ea_localid" value="23509"/>
								<UML:TaggedValue tag="ea_sourceName" value="HY_HydrometricFeature"/>
								<UML:TaggedValue tag="ea_targetName" value="HY_HydroLocation"/>
								<UML:TaggedValue tag="ea_sourceType" value="Class"/>
								<UML:TaggedValue tag="ea_targetType" value="Class"/>
								<UML:TaggedValue tag="ea_sourceID" value="15739"/>
								<UML:TaggedValue tag="ea_targetID" value="15703"/>
								<UML:TaggedValue tag="$ea_xref_property" value="$XREFPROP=$XID={44A84D45-5C6B-4275-AB95-651AE757BAE9}$XID;$NAM=CustomProperties$NAM;$TYP=connector property$TYP;$VIS=Public$VIS;$PAR=0$PAR;$DES=@PROP=@NAME=isDerived@ENDNAME;@TYPE=Boolean@ENDTYPE;@VALU=0@ENDVALU;@PRMT=@ENDPRMT;@ENDPROP;$DES;$CLT={7E04BB82-EFD5-4457-85B3-6BD3A67B53C8}$CLT;$SUP=&lt;none&gt;$SUP;$ENDXREF;"/>
								<UML:TaggedValue tag="$ea_src_xref_property" value="$XREFPROP=$XID={1E2C1CD3-6488-4c59-A557-368EE9D6AB15}$XID;$NAM=CustomProperties$NAM;$TYP=connectorSrcEnd property$TYP;$VIS=Public$VIS;$PAR=0$PAR;$DES=@PROP=@NAME=isComposite@ENDNAME;@TYPE=Boolean@ENDTYPE;@VALU=@ENDVALU;@PRMT=@ENDPRMT;@ENDPROP;@PROP=@NAME=isDerivedUnion@ENDNAME;@TYPE=Boolean@ENDTYPE;@VALU=false@ENDVALU;@PRMT=@ENDPRMT;@ENDPROP;@PROP=@NAME=default@ENDNAME;@TYPE=String@ENDTYPE;@VALU=@ENDVALU;@PRMT=@ENDPRMT;@ENDPROP;@PROP=@NAME=isReadOnly@ENDNAME;@TYPE=Boolean@ENDTYPE;@VALU=false@ENDVALU;@PRMT=@ENDPRMT;@ENDPROP;@PROP=@NAME=isDerived@ENDNAME;@TYPE=Boolean@ENDTYPE;@VALU=false@ENDVALU;@PRMT=@ENDPRMT;@ENDPROP;@PROP=@NAME=aggregation@ENDNAME;@TYPE=AggregationKind@ENDTYPE;@VALU=none@ENDVALU;@PRMT=@ENDPRMT;@ENDPROP;$DES;$CLT={7E04BB82-EFD5-4457-85B3-6BD3A67B53C8}$CLT;$SUP=&lt;none&gt;$SUP;$ENDXREF;"/>
								<UML:TaggedValue tag="$ea_dst_xref_property" value="$XREFPROP=$XID={5B2ECB5F-6C42-4fc0-9BA1-061F13175C09}$XID;$NAM=CustomProperties$NAM;$TYP=connectorDestEnd property$TYP;$VIS=Public$VIS;$PAR=0$PAR;$DES=@PROP=@NAME=isComposite@ENDNAME;@TYPE=Boolean@ENDTYPE;@VALU=@ENDVALU;@PRMT=@ENDPRMT;@ENDPROP;@PROP=@NAME=isDerivedUnion@ENDNAME;@TYPE=Boolean@ENDTYPE;@VALU=false@ENDVALU;@PRMT=@ENDPRMT;@ENDPROP;@PROP=@NAME=default@ENDNAME;@TYPE=String@ENDTYPE;@VALU=@ENDVALU;@PRMT=@ENDPRMT;@ENDPROP;@PROP=@NAME=isReadOnly@ENDNAME;@TYPE=Boolean@ENDTYPE;@VALU=false@ENDVALU;@PRMT=@ENDPRMT;@ENDPROP;@PROP=@NAME=isDerived@ENDNAME;@TYPE=Boolean@ENDTYPE;@VALU=false@ENDVALU;@PRMT=@ENDPRMT;@ENDPROP;@PROP=@NAME=aggregation@ENDNAME;@TYPE=AggregationKind@ENDTYPE;@VALU=none@ENDVALU;@PRMT=@ENDPRMT;@ENDPROP;$DES;$CLT={7E04BB82-EFD5-4457-85B3-6BD3A67B53C8}$CLT;$SUP=&lt;none&gt;$SUP;$ENDXREF;"/>
								<UML:TaggedValue tag="virtualInheritance" value="0"/>
								<UML:TaggedValue tag="rb" value="0..1"/>
								<UML:TaggedValue tag="rt" value="+positionOnRiver"/>
							</UML:ModelElement.taggedValue>
							<UML:Association.connection>
								<UML:AssociationEnd visibility="public" aggregation="none" isOrdered="false" targetScope="instance" changeable="none" isNavigable="false" type="EAID_BB084F13_AED3_4c9d_9E8F_2C46B9CBC703">
									<UML:ModelElement.taggedValue>
										<UML:TaggedValue tag="containment" value="Unspecified"/>
										<UML:TaggedValue tag="sourcestyle" value="Union=0;Derived=0;AllowDuplicates=0;Owned=0;Navigable=Unspecified;"/>
										<UML:TaggedValue tag="ea_end" value="source"/>
									</UML:ModelElement.taggedValue>
								</UML:AssociationEnd>
								<UML:AssociationEnd visibility="public" multiplicity="0..1" name="positionOnRiver" aggregation="none" isOrdered="false" targetScope="instance" changeable="none" isNavigable="true" type="EAID_CBE94F0D_9CA6_4cc3_9730_F0F7F31C2EB4">
									<UML:ModelElement.taggedValue>
										<UML:TaggedValue tag="description" value="identifies the position of the hydrometric feature in the hydrographic network as a hydro location which realizes the hydro nexus of the catchment corresponding to the hydrometric feature.&#xA;&#xA;identifies a fixed landmark which realizes the hydro nexus of the catchment realized by the waterbody as a permanent reference location.&#xA;"/>
										<UML:TaggedValue tag="containment" value="Unspecified"/>
										<UML:TaggedValue tag="deststyle" value="Union=0;Derived=0;AllowDuplicates=0;Owned=0;Navigable=Navigable;"/>
										<UML:TaggedValue tag="ea_end" value="target"/>
									</UML:ModelElement.taggedValue>
								</UML:AssociationEnd>
							</UML:Association.connection>
						</UML:Association>
						<UML:Generalization subtype="EAID_BB084F13_AED3_4c9d_9E8F_2C46B9CBC703" supertype="EAID_A8ACD296_95A0_45f6_961E_4C92E4A95944" xmi.id="EAID_AE0E9EED_29A8_4ae8_98A2_05401A7F956B" visibility="public">
							<UML:ModelElement.taggedValue>
								<UML:TaggedValue tag="style" value="1"/>
								<UML:TaggedValue tag="ea_type" value="Generalization"/>
								<UML:TaggedValue tag="direction" value="Source -&gt; Destination"/>
								<UML:TaggedValue tag="linemode" value="1"/>
								<UML:TaggedValue tag="linecolor" value="-1"/>
								<UML:TaggedValue tag="linewidth" value="0"/>
								<UML:TaggedValue tag="seqno" value="0"/>
								<UML:TaggedValue tag="headStyle" value="0"/>
								<UML:TaggedValue tag="lineStyle" value="0"/>
								<UML:TaggedValue tag="ea_localid" value="23508"/>
								<UML:TaggedValue tag="ea_sourceName" value="HY_HydrometricFeature"/>
								<UML:TaggedValue tag="ea_targetName" value="HY_HydroFeature"/>
								<UML:TaggedValue tag="ea_sourceType" value="Class"/>
								<UML:TaggedValue tag="ea_targetType" value="Class"/>
								<UML:TaggedValue tag="ea_sourceID" value="15739"/>
								<UML:TaggedValue tag="ea_targetID" value="15694"/>
								<UML:TaggedValue tag="src_visibility" value="Public"/>
								<UML:TaggedValue tag="src_aggregation" value="0"/>
								<UML:TaggedValue tag="src_isOrdered" value="false"/>
								<UML:TaggedValue tag="src_targetScope" value="instance"/>
								<UML:TaggedValue tag="src_changeable" value="none"/>
								<UML:TaggedValue tag="src_isNavigable" value="false"/>
								<UML:TaggedValue tag="src_containment" value="Unspecified"/>
								<UML:TaggedValue tag="src_style" value="Union=0;Derived=0;AllowDuplicates=0;"/>
								<UML:TaggedValue tag="dst_visibility" value="Public"/>
								<UML:TaggedValue tag="dst_aggregation" value="0"/>
								<UML:TaggedValue tag="dst_isOrdered" value="false"/>
								<UML:TaggedValue tag="dst_targetScope" value="instance"/>
								<UML:TaggedValue tag="dst_changeable" value="none"/>
								<UML:TaggedValue tag="dst_isNavigable" value="true"/>
								<UML:TaggedValue tag="dst_containment" value="Unspecified"/>
								<UML:TaggedValue tag="dst_style" value="Union=0;Derived=0;AllowDuplicates=0;"/>
								<UML:TaggedValue tag="virtualInheritance" value="0"/>
							</UML:ModelElement.taggedValue>
						</UML:Generalization>
						<UML:Dependency client="EAPK_45020593_84CC_4e21_BA1B_E523CF0BBA0A" supplier="EAPK_D5463997_E01A_47ff_B150_AB5F2622456C" xmi.id="EAID_D0B04AE8_6F20_4e32_95C0_4F08DB3629B8" visibility="public">
							<UML:ModelElement.stereotype>
								<UML:Stereotype name="import"/>
							</UML:ModelElement.stereotype>
							<UML:ModelElement.taggedValue>
								<UML:TaggedValue tag="documentation" value="Created by HollowWorld Plugin"/>
								<UML:TaggedValue tag="style" value="1"/>
								<UML:TaggedValue tag="ea_type" value="Dependency"/>
								<UML:TaggedValue tag="direction" value="Source -&gt; Destination"/>
								<UML:TaggedValue tag="linemode" value="1"/>
								<UML:TaggedValue tag="linecolor" value="-1"/>
								<UML:TaggedValue tag="linewidth" value="0"/>
								<UML:TaggedValue tag="seqno" value="0"/>
								<UML:TaggedValue tag="stereotype" value="import"/>
								<UML:TaggedValue tag="headStyle" value="0"/>
								<UML:TaggedValue tag="lineStyle" value="0"/>
								<UML:TaggedValue tag="conditional" value=" &#xA;쳃mport"/>
								<UML:TaggedValue tag="ea_localid" value="23507"/>
								<UML:TaggedValue tag="ea_sourceName" value="HY_HydrometricNetwork"/>
								<UML:TaggedValue tag="ea_targetName" value="HY_HydroFeature"/>
								<UML:TaggedValue tag="ea_sourceType" value="Package"/>
								<UML:TaggedValue tag="ea_targetType" value="Package"/>
								<UML:TaggedValue tag="ea_sourceID" value="15737"/>
								<UML:TaggedValue tag="ea_targetID" value="15688"/>
								<UML:TaggedValue tag="src_visibility" value="Public"/>
								<UML:TaggedValue tag="src_aggregation" value="0"/>
								<UML:TaggedValue tag="src_isOrdered" value="false"/>
								<UML:TaggedValue tag="src_isNavigable" value="false"/>
								<UML:TaggedValue tag="src_style" value="Owned=0;Navigable=Non-Navigable;"/>
								<UML:TaggedValue tag="dst_visibility" value="Public"/>
								<UML:TaggedValue tag="dst_aggregation" value="0"/>
								<UML:TaggedValue tag="dst_isOrdered" value="false"/>
								<UML:TaggedValue tag="dst_isNavigable" value="false"/>
								<UML:TaggedValue tag="dst_style" value="Owned=0;Navigable=Navigable;"/>
								<UML:TaggedValue tag="virtualInheritance" value="0"/>
								<UML:TaggedValue tag="mb" value=" &#xA;쳃mport"/>
							</UML:ModelElement.taggedValue>
						</UML:Dependency>
						<UML:Dependency client="EAPK_D539B586_0ADB_4882_A8B9_AD6F1E2E34B7" supplier="EAPK_45020593_84CC_4e21_BA1B_E523CF0BBA0A" xmi.id="EAID_4970ADCE_2D31_4f74_B7F2_9B4858AFD08B" visibility="public">
							<UML:ModelElement.stereotype>
								<UML:Stereotype name="import"/>
							</UML:ModelElement.stereotype>
							<UML:ModelElement.taggedValue>
								<UML:TaggedValue tag="style" value="1"/>
								<UML:TaggedValue tag="ea_type" value="Package"/>
								<UML:TaggedValue tag="direction" value="Source -&gt; Destination"/>
								<UML:TaggedValue tag="linemode" value="1"/>
								<UML:TaggedValue tag="linecolor" value="-1"/>
								<UML:TaggedValue tag="linewidth" value="0"/>
								<UML:TaggedValue tag="seqno" value="0"/>
								<UML:TaggedValue tag="stereotype" value="import"/>
								<UML:TaggedValue tag="headStyle" value="0"/>
								<UML:TaggedValue tag="lineStyle" value="0"/>
								<UML:TaggedValue tag="conditional" value=" &#xA;쳃mport"/>
								<UML:TaggedValue tag="ea_localid" value="23515"/>
								<UML:TaggedValue tag="ea_sourceName" value="HY_Features_Hydrology_Model"/>
								<UML:TaggedValue tag="ea_targetName" value="HY_HydrometricNetwork"/>
								<UML:TaggedValue tag="ea_sourceType" value="Package"/>
								<UML:TaggedValue tag="ea_targetType" value="Package"/>
								<UML:TaggedValue tag="ea_sourceID" value="15741"/>
								<UML:TaggedValue tag="ea_targetID" value="15737"/>
								<UML:TaggedValue tag="src_visibility" value="Public"/>
								<UML:TaggedValue tag="src_aggregation" value="0"/>
								<UML:TaggedValue tag="src_isOrdered" value="false"/>
								<UML:TaggedValue tag="src_targetScope" value="instance"/>
								<UML:TaggedValue tag="src_changeable" value="none"/>
								<UML:TaggedValue tag="src_isNavigable" value="false"/>
								<UML:TaggedValue tag="src_containment" value="Unspecified"/>
								<UML:TaggedValue tag="src_style" value="Union=0;Derived=0;AllowDuplicates=0;Owned=0;Navigable=Non-Navigable;"/>
								<UML:TaggedValue tag="dst_visibility" value="Public"/>
								<UML:TaggedValue tag="dst_aggregation" value="0"/>
								<UML:TaggedValue tag="dst_isOrdered" value="false"/>
								<UML:TaggedValue tag="dst_targetScope" value="instance"/>
								<UML:TaggedValue tag="dst_changeable" value="none"/>
								<UML:TaggedValue tag="dst_isNavigable" value="true"/>
								<UML:TaggedValue tag="dst_containment" value="Unspecified"/>
								<UML:TaggedValue tag="dst_style" value="Union=0;Derived=0;AllowDuplicates=0;Owned=0;Navigable=Navigable;"/>
								<UML:TaggedValue tag="$ea_xref_property" value="$XREFPROP=$XID={3BE29405-1461-41ec-AA01-C59887D71B8A}$XID;$NAM=Stereotypes$NAM;$TYP=connector property$TYP;$VIS=Public$VIS;$PAR=0$PAR;$DES=@STEREO;Name=import;GUID={1938445F-D166-47a6-B5FE-58C287DB3CB8};@ENDSTEREO;$DES;$CLT={4970ADCE-2D31-4f74-B7F2-9B4858AFD08B}$CLT;$SUP=&lt;none&gt;$SUP;$ENDXREF;"/>
								<UML:TaggedValue tag="virtualInheritance" value="0"/>
								<UML:TaggedValue tag="mb" value=" &#xA;쳃mport"/>
							</UML:ModelElement.taggedValue>
						</UML:Dependency>
					</UML:Namespace.ownedElement>
				</UML:Package>
				<UML:Stereotype xmi.id="EAID_F2B96478_2A26_4273_A9FA_BE8F2F80BCFC" name="Application Schema" isRoot="false" isLeaf="false" isAbstract="false">
					<UML:Stereotype.baseClass>Package</UML:Stereotype.baseClass>
				</UML:Stereotype>
			</UML:Namespace.ownedElement>
		</UML:Model>
		<UML:Diagram name="Fig45: Hydrometric Feature - Nexus - Catchment" xmi.id="EAID_E8220B60_2F06_4be6_B608_0E3BEDB1F85E" diagramType="DiagramDiagram" owner="EAPK_45020593_84CC_4e21_BA1B_E523CF0BBA0A" toolName="Enterprise Architect 2.5">
			<UML:ModelElement.taggedValue>
				<UML:TaggedValue tag="version" value="1"/>
				<UML:TaggedValue tag="author" value="Solid Ground Add-In"/>
				<UML:TaggedValue tag="created_date" value="2016-07-19 15:40:50"/>
				<UML:TaggedValue tag="modified_date" value="2017-06-01 08:58:45"/>
				<UML:TaggedValue tag="package" value="EAPK_45020593_84CC_4e21_BA1B_E523CF0BBA0A"/>
				<UML:TaggedValue tag="type" value="Diagram"/>
				<UML:TaggedValue tag="swimlanes" value="locked=false;orientation=0;width=0;inbar=false;names=false;color=0;bold=false;fcol=0;;cls=0;"/>
				<UML:TaggedValue tag="matrixitems" value="locked=false;matrixactive=false;swimlanesactive=true;width=1;"/>
				<UML:TaggedValue tag="tpos" value="2"/>
				<UML:TaggedValue tag="ea_localid" value="8133"/>
				<UML:TaggedValue tag="EAStyle" value="ShowPrivate=1;ShowProtected=1;ShowPublic=1;HideRelationships=0;Locked=0;Border=1;HighlightForeign=0;PackageContents=1;SequenceNotes=0;ScalePrintImage=0;PPgs.cx=2;PPgs.cy=1;DocSize.cx=800;DocSize.cy=1100;ShowDetails=0;Orientation=P;Zoom=100;ShowTags=0;OpParams=1;VisibleAttributeDetail=0;ShowOpRetType=1;ShowIcons=1;CollabNums=0;HideProps=0;ShowReqs=0;ShowCons=1;PaperSize=9;HideParents=0;UseAlias=0;HideAtts=0;HideOps=0;HideStereo=0;HideElemStereo=0;ShowTests=0;ShowMaint=0;ConnectorNotation=UML 2.1;ExplicitNavigability=0;AdvancedElementProps=1;AdvancedFeatureProps=1;AdvancedConnectorProps=1;ShowNotes=0;SuppressBrackets=0;SuppConnectorLabels=0;PrintPageHeadFoot=0;ShowAsList=0;"/>
				<UML:TaggedValue tag="styleex" value="SaveTag=A5B370DA;ExcludeRTF=0;DocAll=0;HideQuals=0;AttPkg=1;ShowTests=0;ShowMaint=0;Layout=l=20:c=10:d=0:cr=0:la=2:i=0:it=10:a=0:;SuppressFOC=1;MatrixActive=0;SwimlanesActive=1;MatrixLineWidth=1;MatrixLocked=0;TConnectorNotation=UML 2.1;TExplicitNavigability=0;AdvancedElementProps=1;AdvancedFeatureProps=1;AdvancedConnectorProps=1;ProfileData=;MDGDgm=;STBLDgm=;ShowNotes=0;VisibleAttributeDetail=0;ShowOpRetType=1;SuppressBrackets=0;SuppConnectorLabels=0;PrintPageHeadFoot=0;ShowAsList=0;"/>
			</UML:ModelElement.taggedValue>
			<UML:Diagram.element>
				<UML:DiagramElement geometry="Left=11;Top=154;Right=128;Bottom=216;" subject="EAID_BAEBC4B0_8A02_47df_95C3_C8AE3298EAFE" seqno="1" style="DUID=577A3472;NSL=0;BFol=-1;LCol=-1;LWth=-1;bold=0;italic=0;ul=0;charset=0;font=Arial Narrow;fontsz=100;pitch=34;BCol=16777215;"/>
				<UML:DiagramElement geometry="Left=671;Top=202;Right=769;Bottom=266;" subject="EAID_5BFBF32B_6310_4a1a_92F7_63CDA1849E42" seqno="2" style="DUID=90165DB8;NSL=0;BFol=-1;LCol=-1;LWth=-1;bold=0;italic=0;ul=0;charset=0;font=Arial Narrow;fontsz=100;pitch=34;BCol=16777215;"/>
				<UML:DiagramElement geometry="Left=650;Top=10;Right=800;Bottom=94;" subject="EAID_E67844C9_2AD6_45af_B92B_6AE7C4F88DE6" seqno="3" style="DUID=5D7CC408;NSL=0;BFol=-1;LCol=-1;LWth=-1;bold=0;italic=0;ul=0;charset=0;font=Arial Narrow;fontsz=100;pitch=34;BCol=16777215;"/>
				<UML:DiagramElement geometry="Left=252;Top=277;Right=387;Bottom=355;" subject="EAID_5D9E5E19_3F78_4eb2_94E3_74D083F92886" seqno="4" style="DUID=EB60DA0F;NSL=0;BFol=-1;LCol=-1;LWth=-1;bold=0;italic=0;ul=0;charset=0;Constraint=1;AttCustom=0;OpCustom=0;RzO=1;font=Arial Narrow;fontsz=100;pitch=34;BCol=16777215;"/>
				<UML:DiagramElement geometry="Left=253;Top=419;Right=391;Bottom=536;" subject="EAID_BB084F13_AED3_4c9d_9E8F_2C46B9CBC703" seqno="5" style="DUID=B534C09B;NSL=0;BFol=-1;LCol=-1;LWth=-1;bold=0;italic=0;ul=0;charset=0;Constraint=1;AttCustom=0;OpCustom=0;RzO=1;font=Arial Narrow;fontsz=100;pitch=34;BCol=16777215;"/>
				<UML:DiagramElement geometry="Left=263;Top=154;Right=373;Bottom=217;" subject="EAID_50BFCF9E_F639_4b92_999F_99D1B94B7A45" seqno="6" style="DUID=AE964CA3;NSL=0;BFol=-1;LCol=-1;LWth=-1;bold=0;italic=0;ul=0;charset=0;Constraint=1;AttCustom=0;OpCustom=0;RzO=1;font=Arial Narrow;fontsz=100;pitch=34;BCol=16777215;"/>
				<UML:DiagramElement geometry="Left=126;Top=17;Right=274;Bottom=88;" subject="EAID_F95F2B6D_6CCD_45af_848D_70F197200916" seqno="7" style="DUID=16E5B55D;NSL=0;BFol=-1;LCol=-1;LWth=-1;bold=0;italic=0;ul=0;charset=0;Constraint=1;AttCustom=0;OpCustom=0;RzO=1;font=Arial Narrow;fontsz=100;pitch=34;BCol=16777215;"/>
				<UML:DiagramElement geometry="Left=563;Top=385;Right=864;Bottom=472;" subject="EAID_CBE94F0D_9CA6_4cc3_9730_F0F7F31C2EB4" seqno="8" style="DUID=91656806;NSL=0;BFol=-1;LCol=-1;LWth=-1;bold=0;italic=0;ul=0;charset=0;Constraint=1;AttCustom=0;OpCustom=0;RzO=1;font=Arial Narrow;fontsz=100;pitch=34;BCol=16777215;"/>
				<UML:DiagramElement geometry="EDGE=2;$LLB=CX=16:CY=13:OX=0:OY=0:HDN=0:BLD=0:ITA=0:UND=0:CLR=-1:ALN=0:DIR=0:ROT=0;LLT=CX=109:CY=13:OX=0:OY=0:HDN=0:BLD=0:ITA=0:UND=0:CLR=-1:ALN=0:DIR=0:ROT=0;LMT=;LMB=;LRT=CX=95:CY=13:OX=0:OY=0:HDN=0:BLD=0:ITA=0:UND=0:CLR=-1:ALN=0:DIR=0:ROT=0;LRB=CX=18:CY=13:OX=0:OY=0:HDN=0:BLD=0:ITA=0:UND=0:CLR=-1:ALN=0:DIR=0:ROT=0;IRHS=;ILHS=;Path=;" subject="EAID_CBD24C0A_CBC2_4d2c_AD1A_2E5BDCC47855" style="Mode=1;EOID=5D7CC408;SOID=16E5B55D;Color=-1;LWidth=0;Hidden=0;"/>
				<UML:DiagramElement geometry="EDGE=4;$LLB=;LLT=;LMT=;LMB=;LRT=CX=46:CY=13:OX=0:OY=0:HDN=0:BLD=0:ITA=0:UND=0:CLR=-1:ALN=0:DIR=0:ROT=0;LRB=CX=16:CY=13:OX=0:OY=0:HDN=0:BLD=0:ITA=0:UND=0:CLR=-1:ALN=0:DIR=0:ROT=0;IRHS=;ILHS=;Path=;" subject="EAID_851B8E67_3395_4b5a_BFE3_1E7239E270C2" style="Mode=1;EOID=577A3472;SOID=AE964CA3;Color=-1;LWidth=0;Hidden=0;"/>
				<UML:DiagramElement geometry="EDGE=1;SX=-1;SY=26;EX=-1;EY=1;$LLB=;LLT=;LMT=;LMB=;LRT=;LRB=;IRHS=;ILHS=;Path=;" subject="EAID_8D2C2EAF_343A_42e9_8B62_A5F17EA6FB6B" style="Mode=3;EOID=16E5B55D;SOID=AE964CA3;Color=-1;LWidth=0;Hidden=0;"/>
				<UML:DiagramElement geometry="EDGE=1;SX=0;SY=-2;EX=4;EY=-2;$LLB=CX=16:CY=13:OX=0:OY=0:HDN=0:BLD=0:ITA=0:UND=0:CLR=-1:ALN=0:DIR=0:ROT=0;LLT=CX=75:CY=13:OX=0:OY=0:HDN=0:BLD=0:ITA=0:UND=0:CLR=-1:ALN=0:DIR=0:ROT=0;LMT=;LMB=;LRT=CX=97:CY=13:OX=-2:OY=1:HDN=0:BLD=0:ITA=0:UND=0:CLR=-1:ALN=0:DIR=0:ROT=0;LRB=CX=6:CY=13:OX=0:OY=0:HDN=0:BLD=0:ITA=0:UND=0:CLR=-1:ALN=0:DIR=0:ROT=0;IRHS=;ILHS=;Path=;" subject="EAID_6E676113_264B_403d_AD04_3C48B5DF0C23" style="Mode=3;EOID=EB60DA0F;SOID=B534C09B;Color=-1;LWidth=0;Hidden=0;"/>
				<UML:DiagramElement geometry="EDGE=2;SX=68;SY=22;EX=-8;EY=-27;$LLB=;LLT=;LMT=;LMB=;LRT=CX=81:CY=13:OX=0:OY=0:HDN=0:BLD=0:ITA=0:UND=0:CLR=-1:ALN=0:DIR=0:ROT=0;LRB=CX=18:CY=13:OX=0:OY=0:HDN=0:BLD=0:ITA=0:UND=0:CLR=-1:ALN=0:DIR=0:ROT=0;IRHS=;ILHS=;Path=;" subject="EAID_7E04BB82_EFD5_4457_85B3_6BD3A67B53C8" style="Mode=3;EOID=91656806;SOID=B534C09B;Color=-1;LWidth=0;Hidden=0;"/>
				<UML:DiagramElement geometry="EDGE=1;SX=2;SY=-16;EX=2;EY=-16;$LLB=;LLT=;LMT=;LMB=;LRT=;LRB=;IRHS=;ILHS=;Path=;" subject="EAID_914F43A7_1DA4_411f_9CEA_E5A9A3C8AA82" style="Mode=3;EOID=AE964CA3;SOID=EB60DA0F;Color=-1;LWidth=0;Hidden=0;"/>
				<UML:DiagramElement geometry="SX=-31;SY=-14;EX=-27;EY=-17;EDGE=3;$LLB=CX=16:CY=13:OX=0:OY=0:HDN=0:BLD=0:ITA=0:UND=0:CLR=-1:ALN=0:DIR=0:ROT=0;LLT=CX=113:CY=13:OX=0:OY=0:HDN=0:BLD=0:ITA=0:UND=0:CLR=-1:ALN=0:DIR=0:ROT=0;LMT=;LMB=;LRT=CX=40:CY=13:OX=0:OY=0:HDN=0:BLD=0:ITA=0:UND=0:CLR=-1:ALN=0:DIR=0:ROT=0;LRB=CX=18:CY=13:OX=0:OY=0:HDN=0:BLD=0:ITA=0:UND=0:CLR=-1:ALN=0:DIR=0:ROT=0;IRHS=;ILHS=;Path=;" subject="EAID_2FF4FC56_848E_447e_B750_44A2F25CCAFE" style="Mode=1;EOID=90165DB8;SOID=5D7CC408;Color=-1;LWidth=0;Hidden=0;"/>
				<UML:DiagramElement geometry="SCTR=1;SCME=1;SX=0;SY=0;EX=0;EY=0;EDGE=3;SCTR.LEFT=725;SCTR.TOP=-107;SCTR.RIGHT=765;SCTR.BOTTOM=-76;$LLB=;LLT=;LMT=;LMB=;LRT=;LRB=;IRHS=;ILHS=;Path=725:-94$725:-107$765:-107$765:-94$;" subject="EAID_325579DA_29B8_4a45_8D34_D31BDF4BF995" style="Mode=1;EOID=5D7CC408;SOID=5D7CC408;Color=-1;LWidth=0;Hidden=1;"/>
				<UML:DiagramElement geometry="SCTR=1;SCME=1;SX=0;SY=0;EX=0;EY=0;EDGE=3;SCTR.LEFT=725;SCTR.TOP=-107;SCTR.RIGHT=765;SCTR.BOTTOM=-76;$LLB=;LLT=;LMT=;LMB=;LRT=;LRB=;IRHS=;ILHS=;Path=725:-94$725:-107$765:-107$765:-94$;" subject="EAID_905F3E17_CCF4_4656_82C9_AE8F1180F6BD" style="Mode=1;EOID=5D7CC408;SOID=5D7CC408;Color=-1;LWidth=0;Hidden=1;"/>
				<UML:DiagramElement geometry="SCTR=1;SCME=1;SX=0;SY=0;EX=0;EY=0;EDGE=3;SCTR.LEFT=725;SCTR.TOP=-107;SCTR.RIGHT=765;SCTR.BOTTOM=-76;$LLB=;LLT=;LMT=;LMB=;LRT=;LRB=;IRHS=;ILHS=;Path=725:-94$725:-107$765:-107$765:-94$;" subject="EAID_D0E7BB5A_98BD_455d_BF44_E7D66E867273" style="Mode=1;EOID=5D7CC408;SOID=5D7CC408;Color=-1;LWidth=0;Hidden=1;"/>
				<UML:DiagramElement geometry="SX=2;SY=-3;EX=9;EY=42;EDGE=3;$LLB=CX=18:CY=13:OX=0:OY=0:HDN=0:BLD=0:ITA=0:UND=0:CLR=-1:ALN=0:DIR=0:ROT=0;LLT=CX=72:CY=13:OX=0:OY=0:HDN=0:BLD=0:ITA=0:UND=0:CLR=-1:ALN=0:DIR=0:ROT=0;LMT=;LMB=;LRT=CX=87:CY=13:OX=0:OY=0:HDN=0:BLD=0:ITA=0:UND=0:CLR=-1:ALN=0:DIR=0:ROT=0;LRB=CX=16:CY=13:OX=0:OY=0:HDN=0:BLD=0:ITA=0:UND=0:CLR=-1:ALN=0:DIR=0:ROT=0;IRHS=;ILHS=;Path=;" subject="EAID_41A59D7B_6F91_47b6_8E37_EFBA51A226AD" style="Mode=1;EOID=91656806;SOID=90165DB8;Color=-1;LWidth=0;Hidden=0;"/>
				<UML:DiagramElement geometry="SX=26;SY=11;EX=22;EY=1;EDGE=1;$LLB=CX=18:CY=13:OX=0:OY=0:HDN=0:BLD=0:ITA=0:UND=0:CLR=-1:ALN=0:DIR=0:ROT=0;LLT=CX=34:CY=13:OX=0:OY=0:HDN=0:BLD=0:ITA=0:UND=0:CLR=-1:ALN=0:DIR=0:ROT=0;LMT=;LMB=;LRT=CX=100:CY=13:OX=139:OY=0:HDN=0:BLD=0:ITA=0:UND=0:CLR=-1:ALN=0:DIR=0:ROT=0;LRB=CX=16:CY=13:OX=0:OY=0:HDN=0:BLD=0:ITA=0:UND=0:CLR=-1:ALN=0:DIR=0:ROT=0;IRHS=;ILHS=;Path=;" subject="EAID_E7A6FD99_CBBE_43e8_82B5_FCB85E06537A" style="Mode=1;EOID=5D7CC408;SOID=90165DB8;Color=-1;LWidth=0;Hidden=0;"/>
				<UML:DiagramElement geometry="EDGE=1;$LLB=;LLT=;LMT=;LMB=;LRT=;LRB=;IRHS=;ILHS=;Path=;" subject="EAID_997A2695_5E45_45d4_91BD_65BD3A9FE4F2" style="Mode=1;EOID=16E5B55D;SOID=577A3472;Color=-1;LWidth=0;Hidden=0;"/>
			</UML:Diagram.element>
		</UML:Diagram>
		<UML:Diagram name="Fig44: Package dependencies" xmi.id="EAID_554A88B8_00F5_4a55_AEB0_ACE29F93A4EE" diagramType="PackageDiagram" owner="EAPK_45020593_84CC_4e21_BA1B_E523CF0BBA0A" toolName="Enterprise Architect 2.5">
			<UML:ModelElement.taggedValue>
				<UML:TaggedValue tag="version" value="1"/>
				<UML:TaggedValue tag="author" value="Solid Ground"/>
				<UML:TaggedValue tag="created_date" value="2016-07-20 13:06:47"/>
				<UML:TaggedValue tag="modified_date" value="2017-06-01 08:58:38"/>
				<UML:TaggedValue tag="package" value="EAPK_45020593_84CC_4e21_BA1B_E523CF0BBA0A"/>
				<UML:TaggedValue tag="type" value="Package"/>
				<UML:TaggedValue tag="swimlanes" value="locked=false;orientation=0;width=0;inbar=false;names=false;color=0;bold=false;fcol=0;;cls=0;"/>
				<UML:TaggedValue tag="matrixitems" value="locked=false;matrixactive=false;swimlanesactive=true;width=1;"/>
				<UML:TaggedValue tag="tpos" value="1"/>
				<UML:TaggedValue tag="ea_localid" value="8134"/>
				<UML:TaggedValue tag="EAStyle" value="ShowPrivate=1;ShowProtected=1;ShowPublic=1;HideRelationships=0;Locked=0;Border=1;HighlightForeign=0;PackageContents=1;SequenceNotes=0;ScalePrintImage=0;PPgs.cx=1;PPgs.cy=1;DocSize.cx=800;DocSize.cy=1100;ShowDetails=0;Orientation=P;Zoom=100;ShowTags=0;OpParams=1;VisibleAttributeDetail=0;ShowOpRetType=1;ShowIcons=1;CollabNums=0;HideProps=0;ShowReqs=0;ShowCons=0;PaperSize=9;HideParents=0;UseAlias=0;HideAtts=0;HideOps=0;HideStereo=0;HideElemStereo=0;ShowTests=0;ShowMaint=0;ConnectorNotation=UML 2.1;ExplicitNavigability=0;AdvancedElementProps=1;AdvancedFeatureProps=1;AdvancedConnectorProps=1;ShowNotes=0;SuppressBrackets=0;SuppConnectorLabels=0;PrintPageHeadFoot=0;ShowAsList=0;"/>
				<UML:TaggedValue tag="styleex" value="SaveTag=E607836F;ExcludeRTF=0;DocAll=0;HideQuals=0;AttPkg=1;ShowTests=0;ShowMaint=0;SuppressFOC=1;MatrixActive=0;SwimlanesActive=1;MatrixLineWidth=1;MatrixLocked=0;TConnectorNotation=UML 2.1;TExplicitNavigability=0;AdvancedElementProps=1;AdvancedFeatureProps=1;AdvancedConnectorProps=1;ProfileData=;MDGDgm=;STBLDgm=;ShowNotes=0;VisibleAttributeDetail=0;ShowOpRetType=1;SuppressBrackets=0;SuppConnectorLabels=0;PrintPageHeadFoot=0;ShowAsList=0;"/>
			</UML:ModelElement.taggedValue>
			<UML:Diagram.element>
				<UML:DiagramElement geometry="Left=26;Top=236;Right=184;Bottom=320;" subject="EAID_45020593_84CC_4e21_BA1B_E523CF0BBA0A" seqno="1" style="DUID=08CB9FF3;font=Arial Narrow;fontsz=100;bold=0;italic=0;ul=0;charset=0;pitch=34;"/>
				<UML:DiagramElement geometry="Left=26;Top=30;Right=176;Bottom=130;" subject="EAID_D5463997_E01A_47ff_B150_AB5F2622456C" seqno="2" style="DUID=50F41734;font=Arial Narrow;fontsz=100;bold=0;italic=0;ul=0;charset=0;pitch=34;"/>
				<UML:DiagramElement geometry="SX=0;SY=0;EX=0;EY=0;EDGE=1;$LLB=;LLT=;LMT=;LMB=CX=42:CY=13:OX=0:OY=0:HDN=1:BLD=0:ITA=0:UND=0:CLR=-1:ALN=0:DIR=0:ROT=0;LRT=;LRB=;IRHS=;ILHS=;Path=;" subject="EAID_D0B04AE8_6F20_4e32_95C0_4F08DB3629B8" style="Mode=3;EOID=50F41734;SOID=08CB9FF3;Color=-1;LWidth=0;Hidden=0;"/>
			</UML:Diagram.element>
		</UML:Diagram>
		<UML:Diagram name="Hydrometric Network Classes" xmi.id="EAID_20468C04_AED5_4955_97FF_AB6D474DE74F" diagramType="DiagramDiagram" owner="EAPK_45020593_84CC_4e21_BA1B_E523CF0BBA0A" toolName="Enterprise Architect 2.5">
			<UML:ModelElement.taggedValue>
				<UML:TaggedValue tag="version" value="1"/>
				<UML:TaggedValue tag="author" value="Solid Ground Add-In"/>
				<UML:TaggedValue tag="created_date" value="2017-06-01 08:59:40"/>
				<UML:TaggedValue tag="modified_date" value="2017-06-01 09:00:03"/>
				<UML:TaggedValue tag="package" value="EAPK_45020593_84CC_4e21_BA1B_E523CF0BBA0A"/>
				<UML:TaggedValue tag="type" value="Diagram"/>
				<UML:TaggedValue tag="swimlanes" value="locked=false;orientation=0;width=0;inbar=false;names=false;color=0;bold=false;fcol=0;;cls=0;"/>
				<UML:TaggedValue tag="matrixitems" value="locked=false;matrixactive=false;swimlanesactive=true;width=1;"/>
				<UML:TaggedValue tag="tpos" value="0"/>
				<UML:TaggedValue tag="ea_localid" value="8135"/>
				<UML:TaggedValue tag="EAStyle" value="ShowPrivate=1;ShowProtected=1;ShowPublic=1;HideRelationships=0;Locked=0;Border=1;HighlightForeign=1;PackageContents=1;SequenceNotes=0;ScalePrintImage=0;PPgs.cx=1;PPgs.cy=1;DocSize.cx=800;DocSize.cy=1100;ShowDetails=0;Orientation=P;Zoom=100;ShowTags=0;OpParams=1;VisibleAttributeDetail=0;ShowOpRetType=1;ShowIcons=1;CollabNums=0;HideProps=0;ShowReqs=0;ShowCons=0;PaperSize=9;HideParents=0;UseAlias=0;HideAtts=0;HideOps=0;HideStereo=0;HideElemStereo=0;ShowTests=0;ShowMaint=0;ConnectorNotation=UML 2.1;ExplicitNavigability=0;AdvancedElementProps=1;AdvancedFeatureProps=1;AdvancedConnectorProps=1;ShowNotes=0;SuppressBrackets=0;SuppConnectorLabels=0;PrintPageHeadFoot=0;ShowAsList=0;"/>
				<UML:TaggedValue tag="styleex" value="SaveTag=4A145693;ExcludeRTF=0;DocAll=0;HideQuals=0;AttPkg=1;ShowTests=0;ShowMaint=0;Layout=l=20:c=10:d=0:cr=0:la=2:i=0:it=10:a=0:;SuppressFOC=1;MatrixActive=0;SwimlanesActive=1;MatrixLineWidth=1;MatrixLocked=0;TConnectorNotation=UML 2.1;TExplicitNavigability=0;AdvancedElementProps=1;AdvancedFeatureProps=1;AdvancedConnectorProps=1;ProfileData=;MDGDgm=;STBLDgm=;ShowNotes=0;VisibleAttributeDetail=0;ShowOpRetType=1;SuppressBrackets=0;SuppConnectorLabels=0;PrintPageHeadFoot=0;ShowAsList=0;"/>
			</UML:ModelElement.taggedValue>
			<UML:Diagram.element>
				<UML:DiagramElement geometry="Left=17;Top=174;Right=141;Bottom=244;" subject="EAID_BB084F13_AED3_4c9d_9E8F_2C46B9CBC703" seqno="1" style="DUID=7825E520;"/>
				<UML:DiagramElement geometry="Left=16;Top=25;Right=144;Bottom=95;" subject="EAID_5D9E5E19_3F78_4eb2_94E3_74D083F92886" seqno="2" style="DUID=18384F2F;"/>
				<UML:DiagramElement geometry="SX=0;SY=0;EX=0;EY=0;EDGE=1;$LLB=CX=16:CY=13:OX=0:OY=0:HDN=0:BLD=0:ITA=0:UND=0:CLR=-1:ALN=0:DIR=0:ROT=0;LLT=CX=75:CY=13:OX=0:OY=0:HDN=0:BLD=0:ITA=0:UND=0:CLR=-1:ALN=0:DIR=0:ROT=0;LMT=;LMB=;LRT=CX=97:CY=13:OX=0:OY=0:HDN=0:BLD=0:ITA=0:UND=0:CLR=-1:ALN=0:DIR=0:ROT=0;LRB=CX=6:CY=13:OX=0:OY=0:HDN=0:BLD=0:ITA=0:UND=0:CLR=-1:ALN=0:DIR=0:ROT=0;IRHS=;ILHS=;Path=;" subject="EAID_6E676113_264B_403d_AD04_3C48B5DF0C23" style="Mode=3;EOID=18384F2F;SOID=7825E520;Color=-1;LWidth=0;Hidden=0;"/>
			</UML:Diagram.element>
		</UML:Diagram>
		<UML:DiagramElement geometry="Left=58;Top=225;Right=252;Bottom=318;" subject="EAID_45020593_84CC_4e21_BA1B_E523CF0BBA0A" seqno="3" style="DUID=AA6D50BB;font=Arial Narrow;fontsz=100;bold=0;italic=0;ul=0;charset=0;pitch=34;">
			<UML:ModelElement.taggedValue>
				<UML:TaggedValue tag="diagram_guid" value="EAID_D3E59732_F8FF_4ce6_A182_9AE552B54588"/>
			</UML:ModelElement.taggedValue>
		</UML:DiagramElement>
		<UML:DiagramElement geometry="Left=455;Top=778;Right=649;Bottom=871;" subject="EAID_45020593_84CC_4e21_BA1B_E523CF0BBA0A" seqno="3" style="DUID=525E738D;NSL=0;BFol=-1;LCol=-1;LWth=-1;fontsz=0;bold=0;italic=0;ul=0;charset=0;pitch=0;BCol=16764057;">
			<UML:ModelElement.taggedValue>
				<UML:TaggedValue tag="diagram_guid" value="EAID_83ED3DD9_9203_4a12_9064_0E2F7B0D1B03"/>
			</UML:ModelElement.taggedValue>
		</UML:DiagramElement>
		<UML:DiagramElement geometry="Left=571;Top=447;Right=702;Bottom=517;" subject="EAID_5D9E5E19_3F78_4eb2_94E3_74D083F92886" seqno="4" style="DUID=9FC95EAE;NSL=0;BCol=-1;BFol=-1;LCol=-1;LWth=-1;fontsz=0;bold=0;italic=0;ul=0;charset=0;pitch=0;">
			<UML:ModelElement.taggedValue>
				<UML:TaggedValue tag="diagram_guid" value="EAID_CE77E4A1_E8F8_4a57_91CA_8D0F1EC75445"/>
			</UML:ModelElement.taggedValue>
		</UML:DiagramElement>
		<UML:DiagramElement geometry="Left=570;Top=679;Right=742;Bottom=778;" subject="EAID_5D9E5E19_3F78_4eb2_94E3_74D083F92886" seqno="23" style="DUID=6EDDE815;NSL=0;BCol=-1;BFol=-1;LCol=-1;LWth=-1;fontsz=0;bold=0;italic=0;ul=0;charset=0;pitch=0;Constraint=1;AttCustom=0;OpCustom=0;RzO=1;">
			<UML:ModelElement.taggedValue>
				<UML:TaggedValue tag="diagram_guid" value="EAID_D8FDBF75_7FD2_4679_890C_16F3A6F9C752"/>
			</UML:ModelElement.taggedValue>
		</UML:DiagramElement>
		<UML:DiagramElement geometry="Left=748;Top=456;Right=1010;Bottom=555;" subject="EAID_5D9E5E19_3F78_4eb2_94E3_74D083F92886" seqno="10" style="DUID=8ED6582C;NSL=0;BCol=-1;BFol=-1;LCol=-1;LWth=-1;fontsz=0;bold=0;italic=0;ul=0;charset=0;pitch=0;Constraint=1;AttCustom=0;OpCustom=0;RzO=3;">
			<UML:ModelElement.taggedValue>
				<UML:TaggedValue tag="diagram_guid" value="EAID_E5781FE1_9542_46bc_9B04_CEC52D6738FF"/>
			</UML:ModelElement.taggedValue>
		</UML:DiagramElement>
		<UML:DiagramElement geometry="Left=917;Top=1037;Right=1043;Bottom=1123;" subject="EAID_5D9E5E19_3F78_4eb2_94E3_74D083F92886" seqno="5" style="DUID=C14A78F6;NSL=0;BCol=-1;BFol=-1;LCol=-1;LWth=-1;fontsz=0;bold=0;italic=0;ul=0;charset=0;pitch=0;Constraint=1;AttCustom=0;OpCustom=0;RzO=1;ConInh=1;">
			<UML:ModelElement.taggedValue>
				<UML:TaggedValue tag="diagram_guid" value="EAID_7B58CD34_CED0_47ea_9103_831EEC7B2C90"/>
			</UML:ModelElement.taggedValue>
		</UML:DiagramElement>
		<UML:DiagramElement geometry="Left=133;Top=225;Right=261;Bottom=303;" subject="EAID_5D9E5E19_3F78_4eb2_94E3_74D083F92886" seqno="1" style="DUID=EB60DA0F;NSL=0;BCol=-1;BFol=-1;LCol=-1;LWth=-1;fontsz=0;bold=0;italic=0;ul=0;charset=0;pitch=0;">
			<UML:ModelElement.taggedValue>
				<UML:TaggedValue tag="diagram_guid" value="EAID_19052557_1565_4d61_BC45_0CC382FFD0E5"/>
			</UML:ModelElement.taggedValue>
		</UML:DiagramElement>
		<UML:DiagramElement geometry="Left=520;Top=418;Right=719;Bottom=488;" subject="EAID_BB084F13_AED3_4c9d_9E8F_2C46B9CBC703" seqno="3" style="DUID=188D4BCE;NSL=0;BCol=-1;BFol=-1;LCol=-1;LWth=-1;fontsz=0;bold=0;italic=0;ul=0;charset=0;pitch=0;">
			<UML:ModelElement.taggedValue>
				<UML:TaggedValue tag="diagram_guid" value="EAID_45B6F2CD_C64B_4429_BA42_939006E4E759"/>
			</UML:ModelElement.taggedValue>
		</UML:DiagramElement>
		<UML:DiagramElement geometry="Left=572;Top=571;Right=703;Bottom=641;" subject="EAID_BB084F13_AED3_4c9d_9E8F_2C46B9CBC703" seqno="3" style="DUID=454BA061;NSL=0;BCol=-1;BFol=-1;LCol=-1;LWth=-1;fontsz=0;bold=0;italic=0;ul=0;charset=0;pitch=0;">
			<UML:ModelElement.taggedValue>
				<UML:TaggedValue tag="diagram_guid" value="EAID_CE77E4A1_E8F8_4a57_91CA_8D0F1EC75445"/>
			</UML:ModelElement.taggedValue>
		</UML:DiagramElement>
		<UML:DiagramElement geometry="Left=797;Top=175;Right=928;Bottom=245;" subject="EAID_BB084F13_AED3_4c9d_9E8F_2C46B9CBC703" seqno="3" style="DUID=16ED36EB;NSL=0;BFol=-1;LCol=-1;LWth=-1;bold=0;italic=0;ul=0;charset=0;font=Arial Narrow;fontsz=100;pitch=34;BCol=16777215;">
			<UML:ModelElement.taggedValue>
				<UML:TaggedValue tag="diagram_guid" value="EAID_FF497341_D4FB_4ad0_8507_852367B8C95E"/>
			</UML:ModelElement.taggedValue>
		</UML:DiagramElement>
		<UML:DiagramElement geometry="Left=1195;Top=665;Right=1319;Bottom=735;" subject="EAID_BB084F13_AED3_4c9d_9E8F_2C46B9CBC703" seqno="6" style=" DUID=382C42E1;">
			<UML:ModelElement.taggedValue>
				<UML:TaggedValue tag="diagram_guid" value="EAID_71721FB7_35FC_42cb_98EE_47441A64DF5D"/>
			</UML:ModelElement.taggedValue>
		</UML:DiagramElement>
		<UML:DiagramElement geometry="Left=399;Top=182;Right=530;Bottom=252;" subject="EAID_BB084F13_AED3_4c9d_9E8F_2C46B9CBC703" seqno="2" style="DUID=E5CCC2C0;NSL=0;BCol=-1;BFol=-1;LCol=-1;LWth=-1;fontsz=0;bold=0;italic=0;ul=0;charset=0;pitch=0;">
			<UML:ModelElement.taggedValue>
				<UML:TaggedValue tag="diagram_guid" value="EAID_6FCC5C53_037C_4e30_9CE2_1BE7F41DDF7A"/>
			</UML:ModelElement.taggedValue>
		</UML:DiagramElement>
		<UML:DiagramElement geometry="Left=596;Top=847;Right=727;Bottom=917;" subject="EAID_BB084F13_AED3_4c9d_9E8F_2C46B9CBC703" seqno="21" style="DUID=B760A378;NSL=0;BCol=-1;BFol=-1;LCol=-1;LWth=-1;fontsz=0;bold=0;italic=0;ul=0;charset=0;pitch=0;Constraint=1;AttCustom=0;OpCustom=0;RzO=1;">
			<UML:ModelElement.taggedValue>
				<UML:TaggedValue tag="diagram_guid" value="EAID_D8FDBF75_7FD2_4679_890C_16F3A6F9C752"/>
			</UML:ModelElement.taggedValue>
		</UML:DiagramElement>
		<UML:DiagramElement geometry="Left=792;Top=739;Right=988;Bottom=821;" subject="EAID_BB084F13_AED3_4c9d_9E8F_2C46B9CBC703" seqno="9" style="DUID=A2FE6E95;NSL=0;BCol=-1;BFol=-1;LCol=-1;LWth=-1;fontsz=0;bold=0;italic=0;ul=0;charset=0;pitch=0;Constraint=1;AttCustom=0;OpCustom=0;RzO=3;">
			<UML:ModelElement.taggedValue>
				<UML:TaggedValue tag="diagram_guid" value="EAID_E5781FE1_9542_46bc_9B04_CEC52D6738FF"/>
			</UML:ModelElement.taggedValue>
		</UML:DiagramElement>
		<UML:DiagramElement geometry="Left=1119;Top=1169;Right=1241;Bottom=1271;" subject="EAID_BB084F13_AED3_4c9d_9E8F_2C46B9CBC703" seqno="17" style="DUID=0FC7484C;NSL=0;BCol=-1;BFol=-1;LCol=-1;LWth=-1;fontsz=0;bold=0;italic=0;ul=0;charset=0;pitch=0;Constraint=1;AttCustom=0;OpCustom=0;ConInh=1;RzO=1;">
			<UML:ModelElement.taggedValue>
				<UML:TaggedValue tag="diagram_guid" value="EAID_7B58CD34_CED0_47ea_9103_831EEC7B2C90"/>
			</UML:ModelElement.taggedValue>
		</UML:DiagramElement>
		<UML:DiagramElement geometry="Left=134;Top=394;Right=258;Bottom=472;" subject="EAID_BB084F13_AED3_4c9d_9E8F_2C46B9CBC703" seqno="2" style="DUID=B534C09B;NSL=0;BCol=-1;BFol=-1;LCol=-1;LWth=-1;fontsz=0;bold=0;italic=0;ul=0;charset=0;pitch=0;">
			<UML:ModelElement.taggedValue>
				<UML:TaggedValue tag="diagram_guid" value="EAID_19052557_1565_4d61_BC45_0CC382FFD0E5"/>
			</UML:ModelElement.taggedValue>
		</UML:DiagramElement>
		<UML:DiagramElement geometry="EDGE=1;$LLB=CX=16:CY=13:OX=0:OY=0:HDN=0:BLD=0:ITA=0:UND=0:CLR=-1:ALN=0:DIR=0:ROT=0;LLT=;LMT=;LMB=;LRT=CX=97:CY=13:OX=0:OY=0:HDN=0:BLD=0:ITA=0:UND=0:CLR=-1:ALN=0:DIR=0:ROT=0;LRB=CX=12:CY=13:OX=0:OY=0:HDN=0:BLD=0:ITA=0:UND=0:CLR=-1:ALN=0:DIR=0:ROT=0;IRHS=;ILHS=;" subject="EAID_6E676113_264B_403d_AD04_3C48B5DF0C23" style="Mode=3;EOID=9FC95EAE;SOID=454BA061;Color=-1;LWidth=0;">
			<UML:ModelElement.taggedValue>
				<UML:TaggedValue tag="diagram_guid" value="EAID_CE77E4A1_E8F8_4a57_91CA_8D0F1EC75445"/>
				<UML:TaggedValue tag="hidden" value="0"/>
			</UML:ModelElement.taggedValue>
		</UML:DiagramElement>
		<UML:DiagramElement geometry="EDGE=4;SX=0;SY=0;EX=0;EY=0;$LLB=CX=16:CY=13:OX=0:OY=0:HDN=0:BLD=0:ITA=0:UND=0:CLR=-1:ALN=0:DIR=0:ROT=0;LLT=CX=75:CY=13:OX=0:OY=0:HDN=0:BLD=0:ITA=0:UND=0:CLR=-1:ALN=0:DIR=0:ROT=0;LMT=;LMB=;LRT=CX=97:CY=13:OX=0:OY=0:HDN=0:BLD=0:ITA=0:UND=0:CLR=-1:ALN=0:DIR=0:ROT=0;LRB=CX=6:CY=13:OX=0:OY=0:HDN=0:BLD=0:ITA=0:UND=0:CLR=-1:ALN=0:DIR=0:ROT=0;IRHS=;ILHS=;" subject="EAID_6E676113_264B_403d_AD04_3C48B5DF0C23" style="Mode=3;EOID=C14A78F6;SOID=0FC7484C;Color=-1;LWidth=0;">
			<UML:ModelElement.taggedValue>
				<UML:TaggedValue tag="diagram_guid" value="EAID_7B58CD34_CED0_47ea_9103_831EEC7B2C90"/>
				<UML:TaggedValue tag="hidden" value="0"/>
			</UML:ModelElement.taggedValue>
		</UML:DiagramElement>
		<UML:DiagramElement geometry="EDGE=1;SX=0;SY=0;EX=0;EY=0;$LLB=CX=16:CY=13:OX=0:OY=0:HDN=0:BLD=0:ITA=0:UND=0:CLR=-1:ALN=0:DIR=0:ROT=0;LLT=CX=75:CY=13:OX=0:OY=0:HDN=0:BLD=0:ITA=0:UND=0:CLR=-1:ALN=0:DIR=0:ROT=0;LMT=;LMB=;LRT=CX=97:CY=13:OX=0:OY=0:HDN=0:BLD=0:ITA=0:UND=0:CLR=-1:ALN=0:DIR=0:ROT=0;LRB=CX=6:CY=13:OX=0:OY=0:HDN=0:BLD=0:ITA=0:UND=0:CLR=-1:ALN=0:DIR=0:ROT=0;IRHS=;ILHS=;" subject="EAID_6E676113_264B_403d_AD04_3C48B5DF0C23" style="Mode=3;EOID=6EDDE815;SOID=B760A378;Color=-1;LWidth=0;">
			<UML:ModelElement.taggedValue>
				<UML:TaggedValue tag="diagram_guid" value="EAID_D8FDBF75_7FD2_4679_890C_16F3A6F9C752"/>
				<UML:TaggedValue tag="hidden" value="0"/>
			</UML:ModelElement.taggedValue>
		</UML:DiagramElement>
		<UML:DiagramElement geometry="EDGE=1;SX=-4;SY=-1;EX=-37;EY=1;$LLB=CX=16:CY=13:OX=-2:OY=-5:HDN=0:BLD=0:ITA=0:UND=0:CLR=-1:ALN=0:DIR=0:ROT=0;LLT=CX=75:CY=13:OX=-22:OY=-6:HDN=0:BLD=0:ITA=0:UND=0:CLR=-1:ALN=0:DIR=0:ROT=0;LMT=;LMB=;LRT=CX=97:CY=13:OX=0:OY=0:HDN=0:BLD=0:ITA=0:UND=0:CLR=-1:ALN=0:DIR=0:ROT=0;LRB=CX=6:CY=13:OX=0:OY=0:HDN=0:BLD=0:ITA=0:UND=0:CLR=-1:ALN=0:DIR=0:ROT=0;IRHS=;ILHS=;" subject="EAID_6E676113_264B_403d_AD04_3C48B5DF0C23" style="Mode=3;EOID=8ED6582C;SOID=A2FE6E95;Color=-1;LWidth=0;">
			<UML:ModelElement.taggedValue>
				<UML:TaggedValue tag="diagram_guid" value="EAID_E5781FE1_9542_46bc_9B04_CEC52D6738FF"/>
				<UML:TaggedValue tag="hidden" value="0"/>
			</UML:ModelElement.taggedValue>
		</UML:DiagramElement>
		<UML:DiagramElement geometry="EDGE=1;$LLB=CX=16:CY=13:OX=0:OY=0:HDN=0:BLD=0:ITA=0:UND=0:CLR=-1:ALN=0:DIR=0:ROT=0;LLT=CX=75:CY=13:OX=0:OY=0:HDN=0:BLD=0:ITA=0:UND=0:CLR=-1:ALN=0:DIR=0:ROT=0;LMT=;LMB=;LRT=CX=97:CY=13:OX=31:OY=16:HDN=0:BLD=0:ITA=0:UND=0:CLR=-1:ALN=0:DIR=0:ROT=0;LRB=CX=6:CY=13:OX=0:OY=0:HDN=0:BLD=0:ITA=0:UND=0:CLR=-1:ALN=0:DIR=0:ROT=0;IRHS=;ILHS=;" subject="EAID_6E676113_264B_403d_AD04_3C48B5DF0C23" style="Mode=3;EOID=EB60DA0F;SOID=B534C09B;Color=-1;LWidth=0;">
			<UML:ModelElement.taggedValue>
				<UML:TaggedValue tag="diagram_guid" value="EAID_19052557_1565_4d61_BC45_0CC382FFD0E5"/>
				<UML:TaggedValue tag="hidden" value="0"/>
			</UML:ModelElement.taggedValue>
		</UML:DiagramElement>
		<UML:DiagramElement geometry="EDGE=4;SX=0;SY=0;EX=0;EY=0;$LLB=;LLT=;LMT=;LMB=;LRT=;LRB=;IRHS=;ILHS=;" subject="EAID_914F43A7_1DA4_411f_9CEA_E5A9A3C8AA82" style="Mode=3;EOID=3568F1EE;SOID=C14A78F6;Color=-1;LWidth=0;">
			<UML:ModelElement.taggedValue>
				<UML:TaggedValue tag="diagram_guid" value="EAID_7B58CD34_CED0_47ea_9103_831EEC7B2C90"/>
				<UML:TaggedValue tag="hidden" value="0"/>
			</UML:ModelElement.taggedValue>
		</UML:DiagramElement>
		<UML:DiagramElement geometry="SX=-24;SY=-7;EX=73;EY=-6;EDGE=4;$LLB=;LLT=;LMT=;LMB=;LRT=;LRB=;IRHS=;ILHS=;" subject="EAID_914F43A7_1DA4_411f_9CEA_E5A9A3C8AA82" style="Mode=1;EOID=35091E28;SOID=8ED6582C;Color=-1;LWidth=0;">
			<UML:ModelElement.taggedValue>
				<UML:TaggedValue tag="diagram_guid" value="EAID_E5781FE1_9542_46bc_9B04_CEC52D6738FF"/>
				<UML:TaggedValue tag="hidden" value="0"/>
				<UML:TaggedValue tag="path" value="844:-1029;"/>
			</UML:ModelElement.taggedValue>
		</UML:DiagramElement>
		<UML:DiagramElement geometry="SX=0;SY=0;EX=0;EY=0;EDGE=1;$LLB=;LLT=;LMT=;LMB=;LRT=;LRB=;IRHS=;ILHS=;" subject="EAID_914F43A7_1DA4_411f_9CEA_E5A9A3C8AA82" style="Mode=3;EOID=06533C7A;SOID=6EDDE815;Color=-1;LWidth=0;">
			<UML:ModelElement.taggedValue>
				<UML:TaggedValue tag="diagram_guid" value="EAID_D8FDBF75_7FD2_4679_890C_16F3A6F9C752"/>
				<UML:TaggedValue tag="hidden" value="0"/>
			</UML:ModelElement.taggedValue>
		</UML:DiagramElement>
		<UML:DiagramElement geometry="EDGE=1;$LLB=;LLT=;LMT=;LMB=;LRT=;LRB=;IRHS=;ILHS=;" subject="EAID_914F43A7_1DA4_411f_9CEA_E5A9A3C8AA82" style="Mode=3;EOID=AE964CA3;SOID=EB60DA0F;Color=-1;LWidth=0;">
			<UML:ModelElement.taggedValue>
				<UML:TaggedValue tag="diagram_guid" value="EAID_19052557_1565_4d61_BC45_0CC382FFD0E5"/>
				<UML:TaggedValue tag="hidden" value="0"/>
			</UML:ModelElement.taggedValue>
		</UML:DiagramElement>
		<UML:DiagramElement geometry="EDGE=1;$LLB=CX=16:CY=13:OX=0:OY=0:HDN=0:BLD=0:ITA=0:UND=0:CLR=-1:ALN=0:DIR=0:ROT=0;LLT=;LMT=;LMB=;LRT=CX=97:CY=13:OX=0:OY=0:HDN=0:BLD=0:ITA=0:UND=0:CLR=-1:ALN=0:DIR=0:ROT=0;LRB=CX=12:CY=13:OX=0:OY=0:HDN=0:BLD=0:ITA=0:UND=0:CLR=-1:ALN=0:DIR=0:ROT=0;IRHS=;ILHS=;" subject="EAID_6E676113_264B_403d_AD04_3C48B5DF0C23" style="Mode=3;EOID=9FC95EAE;SOID=454BA061;Color=-1;LWidth=0;">
			<UML:ModelElement.taggedValue>
				<UML:TaggedValue tag="diagram_guid" value="EAID_CE77E4A1_E8F8_4a57_91CA_8D0F1EC75445"/>
				<UML:TaggedValue tag="hidden" value="0"/>
			</UML:ModelElement.taggedValue>
		</UML:DiagramElement>
		<UML:DiagramElement geometry="EDGE=4;SX=0;SY=0;EX=0;EY=0;$LLB=CX=16:CY=13:OX=0:OY=0:HDN=0:BLD=0:ITA=0:UND=0:CLR=-1:ALN=0:DIR=0:ROT=0;LLT=CX=75:CY=13:OX=0:OY=0:HDN=0:BLD=0:ITA=0:UND=0:CLR=-1:ALN=0:DIR=0:ROT=0;LMT=;LMB=;LRT=CX=97:CY=13:OX=0:OY=0:HDN=0:BLD=0:ITA=0:UND=0:CLR=-1:ALN=0:DIR=0:ROT=0;LRB=CX=6:CY=13:OX=0:OY=0:HDN=0:BLD=0:ITA=0:UND=0:CLR=-1:ALN=0:DIR=0:ROT=0;IRHS=;ILHS=;" subject="EAID_6E676113_264B_403d_AD04_3C48B5DF0C23" style="Mode=3;EOID=C14A78F6;SOID=0FC7484C;Color=-1;LWidth=0;">
			<UML:ModelElement.taggedValue>
				<UML:TaggedValue tag="diagram_guid" value="EAID_7B58CD34_CED0_47ea_9103_831EEC7B2C90"/>
				<UML:TaggedValue tag="hidden" value="0"/>
			</UML:ModelElement.taggedValue>
		</UML:DiagramElement>
		<UML:DiagramElement geometry="EDGE=1;SX=0;SY=0;EX=0;EY=0;$LLB=CX=16:CY=13:OX=0:OY=0:HDN=0:BLD=0:ITA=0:UND=0:CLR=-1:ALN=0:DIR=0:ROT=0;LLT=CX=75:CY=13:OX=0:OY=0:HDN=0:BLD=0:ITA=0:UND=0:CLR=-1:ALN=0:DIR=0:ROT=0;LMT=;LMB=;LRT=CX=97:CY=13:OX=0:OY=0:HDN=0:BLD=0:ITA=0:UND=0:CLR=-1:ALN=0:DIR=0:ROT=0;LRB=CX=6:CY=13:OX=0:OY=0:HDN=0:BLD=0:ITA=0:UND=0:CLR=-1:ALN=0:DIR=0:ROT=0;IRHS=;ILHS=;" subject="EAID_6E676113_264B_403d_AD04_3C48B5DF0C23" style="Mode=3;EOID=6EDDE815;SOID=B760A378;Color=-1;LWidth=0;">
			<UML:ModelElement.taggedValue>
				<UML:TaggedValue tag="diagram_guid" value="EAID_D8FDBF75_7FD2_4679_890C_16F3A6F9C752"/>
				<UML:TaggedValue tag="hidden" value="0"/>
			</UML:ModelElement.taggedValue>
		</UML:DiagramElement>
		<UML:DiagramElement geometry="EDGE=1;SX=-4;SY=-1;EX=-37;EY=1;$LLB=CX=16:CY=13:OX=-2:OY=-5:HDN=0:BLD=0:ITA=0:UND=0:CLR=-1:ALN=0:DIR=0:ROT=0;LLT=CX=75:CY=13:OX=-22:OY=-6:HDN=0:BLD=0:ITA=0:UND=0:CLR=-1:ALN=0:DIR=0:ROT=0;LMT=;LMB=;LRT=CX=97:CY=13:OX=0:OY=0:HDN=0:BLD=0:ITA=0:UND=0:CLR=-1:ALN=0:DIR=0:ROT=0;LRB=CX=6:CY=13:OX=0:OY=0:HDN=0:BLD=0:ITA=0:UND=0:CLR=-1:ALN=0:DIR=0:ROT=0;IRHS=;ILHS=;" subject="EAID_6E676113_264B_403d_AD04_3C48B5DF0C23" style="Mode=3;EOID=8ED6582C;SOID=A2FE6E95;Color=-1;LWidth=0;">
			<UML:ModelElement.taggedValue>
				<UML:TaggedValue tag="diagram_guid" value="EAID_E5781FE1_9542_46bc_9B04_CEC52D6738FF"/>
				<UML:TaggedValue tag="hidden" value="0"/>
			</UML:ModelElement.taggedValue>
		</UML:DiagramElement>
		<UML:DiagramElement geometry="EDGE=1;$LLB=CX=16:CY=13:OX=0:OY=0:HDN=0:BLD=0:ITA=0:UND=0:CLR=-1:ALN=0:DIR=0:ROT=0;LLT=CX=75:CY=13:OX=0:OY=0:HDN=0:BLD=0:ITA=0:UND=0:CLR=-1:ALN=0:DIR=0:ROT=0;LMT=;LMB=;LRT=CX=97:CY=13:OX=31:OY=16:HDN=0:BLD=0:ITA=0:UND=0:CLR=-1:ALN=0:DIR=0:ROT=0;LRB=CX=6:CY=13:OX=0:OY=0:HDN=0:BLD=0:ITA=0:UND=0:CLR=-1:ALN=0:DIR=0:ROT=0;IRHS=;ILHS=;" subject="EAID_6E676113_264B_403d_AD04_3C48B5DF0C23" style="Mode=3;EOID=EB60DA0F;SOID=B534C09B;Color=-1;LWidth=0;">
			<UML:ModelElement.taggedValue>
				<UML:TaggedValue tag="diagram_guid" value="EAID_19052557_1565_4d61_BC45_0CC382FFD0E5"/>
				<UML:TaggedValue tag="hidden" value="0"/>
			</UML:ModelElement.taggedValue>
		</UML:DiagramElement>
		<UML:DiagramElement geometry="EDGE=4;SX=0;SY=0;EX=0;EY=0;$LLB=;LLT=;LMT=;LMB=;LRT=;LRB=;IRHS=;ILHS=;" subject="EAID_914F43A7_1DA4_411f_9CEA_E5A9A3C8AA82" style="Mode=3;EOID=3568F1EE;SOID=C14A78F6;Color=-1;LWidth=0;">
			<UML:ModelElement.taggedValue>
				<UML:TaggedValue tag="diagram_guid" value="EAID_7B58CD34_CED0_47ea_9103_831EEC7B2C90"/>
				<UML:TaggedValue tag="hidden" value="0"/>
			</UML:ModelElement.taggedValue>
		</UML:DiagramElement>
		<UML:DiagramElement geometry="SX=-24;SY=-7;EX=73;EY=-6;EDGE=4;$LLB=;LLT=;LMT=;LMB=;LRT=;LRB=;IRHS=;ILHS=;" subject="EAID_914F43A7_1DA4_411f_9CEA_E5A9A3C8AA82" style="Mode=1;EOID=35091E28;SOID=8ED6582C;Color=-1;LWidth=0;">
			<UML:ModelElement.taggedValue>
				<UML:TaggedValue tag="diagram_guid" value="EAID_E5781FE1_9542_46bc_9B04_CEC52D6738FF"/>
				<UML:TaggedValue tag="hidden" value="0"/>
				<UML:TaggedValue tag="path" value="844:-1029;"/>
			</UML:ModelElement.taggedValue>
		</UML:DiagramElement>
		<UML:DiagramElement geometry="SX=0;SY=0;EX=0;EY=0;EDGE=1;$LLB=;LLT=;LMT=;LMB=;LRT=;LRB=;IRHS=;ILHS=;" subject="EAID_914F43A7_1DA4_411f_9CEA_E5A9A3C8AA82" style="Mode=3;EOID=06533C7A;SOID=6EDDE815;Color=-1;LWidth=0;">
			<UML:ModelElement.taggedValue>
				<UML:TaggedValue tag="diagram_guid" value="EAID_D8FDBF75_7FD2_4679_890C_16F3A6F9C752"/>
				<UML:TaggedValue tag="hidden" value="0"/>
			</UML:ModelElement.taggedValue>
		</UML:DiagramElement>
		<UML:DiagramElement geometry="EDGE=1;$LLB=;LLT=;LMT=;LMB=;LRT=;LRB=;IRHS=;ILHS=;" subject="EAID_914F43A7_1DA4_411f_9CEA_E5A9A3C8AA82" style="Mode=3;EOID=AE964CA3;SOID=EB60DA0F;Color=-1;LWidth=0;">
			<UML:ModelElement.taggedValue>
				<UML:TaggedValue tag="diagram_guid" value="EAID_19052557_1565_4d61_BC45_0CC382FFD0E5"/>
				<UML:TaggedValue tag="hidden" value="0"/>
			</UML:ModelElement.taggedValue>
		</UML:DiagramElement>
		<UML:DiagramElement geometry="EDGE=1;$LLB=CX=16:CY=13:OX=0:OY=0:HDN=0:BLD=0:ITA=0:UND=0:CLR=-1:ALN=0:DIR=0:ROT=0;LLT=;LMT=;LMB=;LRT=CX=97:CY=13:OX=0:OY=0:HDN=0:BLD=0:ITA=0:UND=0:CLR=-1:ALN=0:DIR=0:ROT=0;LRB=CX=12:CY=13:OX=0:OY=0:HDN=0:BLD=0:ITA=0:UND=0:CLR=-1:ALN=0:DIR=0:ROT=0;IRHS=;ILHS=;" subject="EAID_6E676113_264B_403d_AD04_3C48B5DF0C23" style="Mode=3;EOID=9FC95EAE;SOID=454BA061;Color=-1;LWidth=0;">
			<UML:ModelElement.taggedValue>
				<UML:TaggedValue tag="diagram_guid" value="EAID_CE77E4A1_E8F8_4a57_91CA_8D0F1EC75445"/>
				<UML:TaggedValue tag="hidden" value="0"/>
			</UML:ModelElement.taggedValue>
		</UML:DiagramElement>
		<UML:DiagramElement geometry="EDGE=4;SX=0;SY=0;EX=0;EY=0;$LLB=CX=16:CY=13:OX=0:OY=0:HDN=0:BLD=0:ITA=0:UND=0:CLR=-1:ALN=0:DIR=0:ROT=0;LLT=CX=75:CY=13:OX=0:OY=0:HDN=0:BLD=0:ITA=0:UND=0:CLR=-1:ALN=0:DIR=0:ROT=0;LMT=;LMB=;LRT=CX=97:CY=13:OX=0:OY=0:HDN=0:BLD=0:ITA=0:UND=0:CLR=-1:ALN=0:DIR=0:ROT=0;LRB=CX=6:CY=13:OX=0:OY=0:HDN=0:BLD=0:ITA=0:UND=0:CLR=-1:ALN=0:DIR=0:ROT=0;IRHS=;ILHS=;" subject="EAID_6E676113_264B_403d_AD04_3C48B5DF0C23" style="Mode=3;EOID=C14A78F6;SOID=0FC7484C;Color=-1;LWidth=0;">
			<UML:ModelElement.taggedValue>
				<UML:TaggedValue tag="diagram_guid" value="EAID_7B58CD34_CED0_47ea_9103_831EEC7B2C90"/>
				<UML:TaggedValue tag="hidden" value="0"/>
			</UML:ModelElement.taggedValue>
		</UML:DiagramElement>
		<UML:DiagramElement geometry="EDGE=1;SX=0;SY=0;EX=0;EY=0;$LLB=CX=16:CY=13:OX=0:OY=0:HDN=0:BLD=0:ITA=0:UND=0:CLR=-1:ALN=0:DIR=0:ROT=0;LLT=CX=75:CY=13:OX=0:OY=0:HDN=0:BLD=0:ITA=0:UND=0:CLR=-1:ALN=0:DIR=0:ROT=0;LMT=;LMB=;LRT=CX=97:CY=13:OX=0:OY=0:HDN=0:BLD=0:ITA=0:UND=0:CLR=-1:ALN=0:DIR=0:ROT=0;LRB=CX=6:CY=13:OX=0:OY=0:HDN=0:BLD=0:ITA=0:UND=0:CLR=-1:ALN=0:DIR=0:ROT=0;IRHS=;ILHS=;" subject="EAID_6E676113_264B_403d_AD04_3C48B5DF0C23" style="Mode=3;EOID=6EDDE815;SOID=B760A378;Color=-1;LWidth=0;">
			<UML:ModelElement.taggedValue>
				<UML:TaggedValue tag="diagram_guid" value="EAID_D8FDBF75_7FD2_4679_890C_16F3A6F9C752"/>
				<UML:TaggedValue tag="hidden" value="0"/>
			</UML:ModelElement.taggedValue>
		</UML:DiagramElement>
		<UML:DiagramElement geometry="EDGE=1;SX=-4;SY=-1;EX=-37;EY=1;$LLB=CX=16:CY=13:OX=-2:OY=-5:HDN=0:BLD=0:ITA=0:UND=0:CLR=-1:ALN=0:DIR=0:ROT=0;LLT=CX=75:CY=13:OX=-22:OY=-6:HDN=0:BLD=0:ITA=0:UND=0:CLR=-1:ALN=0:DIR=0:ROT=0;LMT=;LMB=;LRT=CX=97:CY=13:OX=0:OY=0:HDN=0:BLD=0:ITA=0:UND=0:CLR=-1:ALN=0:DIR=0:ROT=0;LRB=CX=6:CY=13:OX=0:OY=0:HDN=0:BLD=0:ITA=0:UND=0:CLR=-1:ALN=0:DIR=0:ROT=0;IRHS=;ILHS=;" subject="EAID_6E676113_264B_403d_AD04_3C48B5DF0C23" style="Mode=3;EOID=8ED6582C;SOID=A2FE6E95;Color=-1;LWidth=0;">
			<UML:ModelElement.taggedValue>
				<UML:TaggedValue tag="diagram_guid" value="EAID_E5781FE1_9542_46bc_9B04_CEC52D6738FF"/>
				<UML:TaggedValue tag="hidden" value="0"/>
			</UML:ModelElement.taggedValue>
		</UML:DiagramElement>
		<UML:DiagramElement geometry="EDGE=1;$LLB=CX=16:CY=13:OX=0:OY=0:HDN=0:BLD=0:ITA=0:UND=0:CLR=-1:ALN=0:DIR=0:ROT=0;LLT=CX=75:CY=13:OX=0:OY=0:HDN=0:BLD=0:ITA=0:UND=0:CLR=-1:ALN=0:DIR=0:ROT=0;LMT=;LMB=;LRT=CX=97:CY=13:OX=31:OY=16:HDN=0:BLD=0:ITA=0:UND=0:CLR=-1:ALN=0:DIR=0:ROT=0;LRB=CX=6:CY=13:OX=0:OY=0:HDN=0:BLD=0:ITA=0:UND=0:CLR=-1:ALN=0:DIR=0:ROT=0;IRHS=;ILHS=;" subject="EAID_6E676113_264B_403d_AD04_3C48B5DF0C23" style="Mode=3;EOID=EB60DA0F;SOID=B534C09B;Color=-1;LWidth=0;">
			<UML:ModelElement.taggedValue>
				<UML:TaggedValue tag="diagram_guid" value="EAID_19052557_1565_4d61_BC45_0CC382FFD0E5"/>
				<UML:TaggedValue tag="hidden" value="0"/>
			</UML:ModelElement.taggedValue>
		</UML:DiagramElement>
		<UML:DiagramElement geometry="SX=0;SY=0;EX=0;EY=0;EDGE=4;$LLB=;LLT=;LMT=;LMB=;LRT=CX=81:CY=13:OX=0:OY=0:HDN=0:BLD=0:ITA=0:UND=0:CLR=-1:ALN=0:DIR=0:ROT=0;LRB=CX=18:CY=13:OX=0:OY=0:HDN=0:BLD=0:ITA=0:UND=0:CLR=-1:ALN=0:DIR=0:ROT=0;IRHS=;ILHS=;" subject="EAID_7E04BB82_EFD5_4457_85B3_6BD3A67B53C8" style="Mode=3;EOID=5179FA81;SOID=382C42E1;Color=-1;LWidth=0;">
			<UML:ModelElement.taggedValue>
				<UML:TaggedValue tag="diagram_guid" value="EAID_71721FB7_35FC_42cb_98EE_47441A64DF5D"/>
				<UML:TaggedValue tag="hidden" value="0"/>
			</UML:ModelElement.taggedValue>
		</UML:DiagramElement>
		<UML:DiagramElement geometry="EDGE=1;$LLB=;LLT=;LMT=;LMB=;LRT=CX=81:CY=13:OX=0:OY=0:HDN=0:BLD=0:ITA=0:UND=0:CLR=-1:ALN=0:DIR=0:ROT=0;LRB=CX=18:CY=13:OX=0:OY=0:HDN=0:BLD=0:ITA=0:UND=0:CLR=-1:ALN=0:DIR=0:ROT=0;IRHS=;ILHS=;" subject="EAID_7E04BB82_EFD5_4457_85B3_6BD3A67B53C8" style="Mode=3;EOID=9E64E8D6;SOID=188D4BCE;Color=-1;LWidth=0;">
			<UML:ModelElement.taggedValue>
				<UML:TaggedValue tag="diagram_guid" value="EAID_45B6F2CD_C64B_4429_BA42_939006E4E759"/>
				<UML:TaggedValue tag="hidden" value="0"/>
			</UML:ModelElement.taggedValue>
		</UML:DiagramElement>
		<UML:DiagramElement geometry="SX=90;SY=-3;EX=-87;EY=-33;EDGE=2;$LLB=;LLT=;LMT=;LMB=;LRT=CX=81:CY=13:OX=44:OY=67:HDN=0:BLD=0:ITA=0:UND=0:CLR=-1:ALN=0:DIR=0:ROT=0;LRB=CX=18:CY=13:OX=-2:OY=-2:HDN=0:BLD=0:ITA=0:UND=0:CLR=-1:ALN=0:DIR=0:ROT=0;IRHS=;ILHS=;" subject="EAID_7E04BB82_EFD5_4457_85B3_6BD3A67B53C8" style="Mode=3;EOID=98C4AA5D;SOID=A2FE6E95;Color=-1;LWidth=0;">
			<UML:ModelElement.taggedValue>
				<UML:TaggedValue tag="diagram_guid" value="EAID_E5781FE1_9542_46bc_9B04_CEC52D6738FF"/>
				<UML:TaggedValue tag="hidden" value="0"/>
				<UML:TaggedValue tag="path" value="1022:-783;"/>
			</UML:ModelElement.taggedValue>
		</UML:DiagramElement>
		<UML:DiagramElement geometry="SX=0;SY=0;EX=0;EY=0;EDGE=1;$LLB=;LLT=;LMT=;LMB=;LRT=CX=81:CY=13:OX=-27:OY=25:HDN=0:BLD=0:ITA=0:UND=0:CLR=-1:ALN=0:DIR=0:ROT=0;LRB=CX=18:CY=13:OX=0:OY=0:HDN=0:BLD=0:ITA=0:UND=0:CLR=-1:ALN=0:DIR=0:ROT=0;IRHS=;ILHS=;" subject="EAID_7E04BB82_EFD5_4457_85B3_6BD3A67B53C8" style="Mode=3;EOID=92E5325F;SOID=0FC7484C;Color=-1;LWidth=0;">
			<UML:ModelElement.taggedValue>
				<UML:TaggedValue tag="diagram_guid" value="EAID_7B58CD34_CED0_47ea_9103_831EEC7B2C90"/>
				<UML:TaggedValue tag="hidden" value="0"/>
				<UML:TaggedValue tag="path" value="1120:-1080;1120:-960;1120:-840;1120:-720;1120:-620;1120:-560;1120:-500;"/>
			</UML:ModelElement.taggedValue>
		</UML:DiagramElement>
		<UML:DiagramElement geometry="EDGE=4;$LLB=;LLT=;LMT=;LMB=;LRT=CX=81:CY=13:OX=0:OY=0:HDN=0:BLD=0:ITA=0:UND=0:CLR=-1:ALN=0:DIR=0:ROT=0;LRB=CX=18:CY=13:OX=0:OY=0:HDN=0:BLD=0:ITA=0:UND=0:CLR=-1:ALN=0:DIR=0:ROT=0;IRHS=;ILHS=;" subject="EAID_7E04BB82_EFD5_4457_85B3_6BD3A67B53C8" style="Mode=1;EOID=268D421D;SOID=E5CCC2C0;Color=-1;LWidth=0;">
			<UML:ModelElement.taggedValue>
				<UML:TaggedValue tag="diagram_guid" value="EAID_6FCC5C53_037C_4e30_9CE2_1BE7F41DDF7A"/>
				<UML:TaggedValue tag="hidden" value="0"/>
			</UML:ModelElement.taggedValue>
		</UML:DiagramElement>
		<UML:DiagramElement geometry="EDGE=2;$LLB=;LLT=;LMT=;LMB=;LRT=CX=81:CY=13:OX=0:OY=0:HDN=0:BLD=0:ITA=0:UND=0:CLR=-1:ALN=0:DIR=0:ROT=0;LRB=CX=18:CY=13:OX=0:OY=0:HDN=0:BLD=0:ITA=0:UND=0:CLR=-1:ALN=0:DIR=0:ROT=0;IRHS=;ILHS=;" subject="EAID_7E04BB82_EFD5_4457_85B3_6BD3A67B53C8" style="Mode=3;EOID=91656806;SOID=B534C09B;Color=-1;LWidth=0;">
			<UML:ModelElement.taggedValue>
				<UML:TaggedValue tag="diagram_guid" value="EAID_19052557_1565_4d61_BC45_0CC382FFD0E5"/>
				<UML:TaggedValue tag="hidden" value="0"/>
			</UML:ModelElement.taggedValue>
		</UML:DiagramElement>
		<UML:DiagramElement geometry="EDGE=2;SX=0;SY=18;EX=0;EY=7;$LLB=;LLT=;LMT=;LMB=;LRT=CX=81:CY=13:OX=-4:OY=5:HDN=0:BLD=0:ITA=0:UND=0:CLR=-1:ALN=0:DIR=0:ROT=0;LRB=CX=18:CY=13:OX=-13:OY=-3:HDN=0:BLD=0:ITA=0:UND=0:CLR=-1:ALN=0:DIR=0:ROT=0;IRHS=;ILHS=;" subject="EAID_7E04BB82_EFD5_4457_85B3_6BD3A67B53C8" style="Mode=3;EOID=E63B968E;SOID=B760A378;Color=-1;LWidth=0;">
			<UML:ModelElement.taggedValue>
				<UML:TaggedValue tag="diagram_guid" value="EAID_D8FDBF75_7FD2_4679_890C_16F3A6F9C752"/>
				<UML:TaggedValue tag="hidden" value="0"/>
			</UML:ModelElement.taggedValue>
		</UML:DiagramElement>
		<UML:DiagramElement geometry="SX=65;SY=-15;EX=55;EY=-35;EDGE=1;$LLB=;LLT=;LMT=;LMB=;LRT=;LRB=;IRHS=;ILHS=;" subject="EAID_AE0E9EED_29A8_4ae8_98A2_05401A7F956B" style="Mode=3;EOID=9B7F3B21;SOID=16ED36EB;Color=-1;LWidth=0;">
			<UML:ModelElement.taggedValue>
				<UML:TaggedValue tag="diagram_guid" value="EAID_FF497341_D4FB_4ad0_8507_852367B8C95E"/>
				<UML:TaggedValue tag="hidden" value="0"/>
			</UML:ModelElement.taggedValue>
		</UML:DiagramElement>
		<UML:DiagramElement geometry="EDGE=1;$LLB=;LLT=;LMT=;LMB=;LRT=;LRB=;IRHS=;ILHS=;" subject="EAID_AE0E9EED_29A8_4ae8_98A2_05401A7F956B" style="Mode=3;EOID=46737D46;SOID=B760A378;Color=-1;LWidth=0;">
			<UML:ModelElement.taggedValue>
				<UML:TaggedValue tag="diagram_guid" value="EAID_D8FDBF75_7FD2_4679_890C_16F3A6F9C752"/>
				<UML:TaggedValue tag="hidden" value="0"/>
			</UML:ModelElement.taggedValue>
		</UML:DiagramElement>
		<UML:DiagramElement geometry="EDGE=1;$LLB=CX=16:CY=13:OX=0:OY=0:HDN=0:BLD=0:ITA=0:UND=0:CLR=-1:ALN=0:DIR=0:ROT=0;LLT=;LMT=;LMB=;LRT=CX=97:CY=13:OX=0:OY=0:HDN=0:BLD=0:ITA=0:UND=0:CLR=-1:ALN=0:DIR=0:ROT=0;LRB=CX=12:CY=13:OX=0:OY=0:HDN=0:BLD=0:ITA=0:UND=0:CLR=-1:ALN=0:DIR=0:ROT=0;IRHS=;ILHS=;" subject="EAID_6E676113_264B_403d_AD04_3C48B5DF0C23" style="Mode=3;EOID=9FC95EAE;SOID=454BA061;Color=-1;LWidth=0;">
			<UML:ModelElement.taggedValue>
				<UML:TaggedValue tag="diagram_guid" value="EAID_CE77E4A1_E8F8_4a57_91CA_8D0F1EC75445"/>
				<UML:TaggedValue tag="hidden" value="0"/>
			</UML:ModelElement.taggedValue>
		</UML:DiagramElement>
		<UML:DiagramElement geometry="EDGE=4;SX=0;SY=0;EX=0;EY=0;$LLB=CX=16:CY=13:OX=0:OY=0:HDN=0:BLD=0:ITA=0:UND=0:CLR=-1:ALN=0:DIR=0:ROT=0;LLT=CX=75:CY=13:OX=0:OY=0:HDN=0:BLD=0:ITA=0:UND=0:CLR=-1:ALN=0:DIR=0:ROT=0;LMT=;LMB=;LRT=CX=97:CY=13:OX=0:OY=0:HDN=0:BLD=0:ITA=0:UND=0:CLR=-1:ALN=0:DIR=0:ROT=0;LRB=CX=6:CY=13:OX=0:OY=0:HDN=0:BLD=0:ITA=0:UND=0:CLR=-1:ALN=0:DIR=0:ROT=0;IRHS=;ILHS=;" subject="EAID_6E676113_264B_403d_AD04_3C48B5DF0C23" style="Mode=3;EOID=C14A78F6;SOID=0FC7484C;Color=-1;LWidth=0;">
			<UML:ModelElement.taggedValue>
				<UML:TaggedValue tag="diagram_guid" value="EAID_7B58CD34_CED0_47ea_9103_831EEC7B2C90"/>
				<UML:TaggedValue tag="hidden" value="0"/>
			</UML:ModelElement.taggedValue>
		</UML:DiagramElement>
		<UML:DiagramElement geometry="EDGE=1;SX=0;SY=0;EX=0;EY=0;$LLB=CX=16:CY=13:OX=0:OY=0:HDN=0:BLD=0:ITA=0:UND=0:CLR=-1:ALN=0:DIR=0:ROT=0;LLT=CX=75:CY=13:OX=0:OY=0:HDN=0:BLD=0:ITA=0:UND=0:CLR=-1:ALN=0:DIR=0:ROT=0;LMT=;LMB=;LRT=CX=97:CY=13:OX=0:OY=0:HDN=0:BLD=0:ITA=0:UND=0:CLR=-1:ALN=0:DIR=0:ROT=0;LRB=CX=6:CY=13:OX=0:OY=0:HDN=0:BLD=0:ITA=0:UND=0:CLR=-1:ALN=0:DIR=0:ROT=0;IRHS=;ILHS=;" subject="EAID_6E676113_264B_403d_AD04_3C48B5DF0C23" style="Mode=3;EOID=6EDDE815;SOID=B760A378;Color=-1;LWidth=0;">
			<UML:ModelElement.taggedValue>
				<UML:TaggedValue tag="diagram_guid" value="EAID_D8FDBF75_7FD2_4679_890C_16F3A6F9C752"/>
				<UML:TaggedValue tag="hidden" value="0"/>
			</UML:ModelElement.taggedValue>
		</UML:DiagramElement>
		<UML:DiagramElement geometry="EDGE=1;SX=-4;SY=-1;EX=-37;EY=1;$LLB=CX=16:CY=13:OX=-2:OY=-5:HDN=0:BLD=0:ITA=0:UND=0:CLR=-1:ALN=0:DIR=0:ROT=0;LLT=CX=75:CY=13:OX=-22:OY=-6:HDN=0:BLD=0:ITA=0:UND=0:CLR=-1:ALN=0:DIR=0:ROT=0;LMT=;LMB=;LRT=CX=97:CY=13:OX=0:OY=0:HDN=0:BLD=0:ITA=0:UND=0:CLR=-1:ALN=0:DIR=0:ROT=0;LRB=CX=6:CY=13:OX=0:OY=0:HDN=0:BLD=0:ITA=0:UND=0:CLR=-1:ALN=0:DIR=0:ROT=0;IRHS=;ILHS=;" subject="EAID_6E676113_264B_403d_AD04_3C48B5DF0C23" style="Mode=3;EOID=8ED6582C;SOID=A2FE6E95;Color=-1;LWidth=0;">
			<UML:ModelElement.taggedValue>
				<UML:TaggedValue tag="diagram_guid" value="EAID_E5781FE1_9542_46bc_9B04_CEC52D6738FF"/>
				<UML:TaggedValue tag="hidden" value="0"/>
			</UML:ModelElement.taggedValue>
		</UML:DiagramElement>
		<UML:DiagramElement geometry="EDGE=1;$LLB=CX=16:CY=13:OX=0:OY=0:HDN=0:BLD=0:ITA=0:UND=0:CLR=-1:ALN=0:DIR=0:ROT=0;LLT=CX=75:CY=13:OX=0:OY=0:HDN=0:BLD=0:ITA=0:UND=0:CLR=-1:ALN=0:DIR=0:ROT=0;LMT=;LMB=;LRT=CX=97:CY=13:OX=31:OY=16:HDN=0:BLD=0:ITA=0:UND=0:CLR=-1:ALN=0:DIR=0:ROT=0;LRB=CX=6:CY=13:OX=0:OY=0:HDN=0:BLD=0:ITA=0:UND=0:CLR=-1:ALN=0:DIR=0:ROT=0;IRHS=;ILHS=;" subject="EAID_6E676113_264B_403d_AD04_3C48B5DF0C23" style="Mode=3;EOID=EB60DA0F;SOID=B534C09B;Color=-1;LWidth=0;">
			<UML:ModelElement.taggedValue>
				<UML:TaggedValue tag="diagram_guid" value="EAID_19052557_1565_4d61_BC45_0CC382FFD0E5"/>
				<UML:TaggedValue tag="hidden" value="0"/>
			</UML:ModelElement.taggedValue>
		</UML:DiagramElement>
		<UML:DiagramElement geometry="SX=0;SY=0;EX=0;EY=0;EDGE=4;$LLB=;LLT=;LMT=;LMB=;LRT=CX=81:CY=13:OX=0:OY=0:HDN=0:BLD=0:ITA=0:UND=0:CLR=-1:ALN=0:DIR=0:ROT=0;LRB=CX=18:CY=13:OX=0:OY=0:HDN=0:BLD=0:ITA=0:UND=0:CLR=-1:ALN=0:DIR=0:ROT=0;IRHS=;ILHS=;" subject="EAID_7E04BB82_EFD5_4457_85B3_6BD3A67B53C8" style="Mode=3;EOID=5179FA81;SOID=382C42E1;Color=-1;LWidth=0;">
			<UML:ModelElement.taggedValue>
				<UML:TaggedValue tag="diagram_guid" value="EAID_71721FB7_35FC_42cb_98EE_47441A64DF5D"/>
				<UML:TaggedValue tag="hidden" value="0"/>
			</UML:ModelElement.taggedValue>
		</UML:DiagramElement>
		<UML:DiagramElement geometry="EDGE=1;$LLB=;LLT=;LMT=;LMB=;LRT=CX=81:CY=13:OX=0:OY=0:HDN=0:BLD=0:ITA=0:UND=0:CLR=-1:ALN=0:DIR=0:ROT=0;LRB=CX=18:CY=13:OX=0:OY=0:HDN=0:BLD=0:ITA=0:UND=0:CLR=-1:ALN=0:DIR=0:ROT=0;IRHS=;ILHS=;" subject="EAID_7E04BB82_EFD5_4457_85B3_6BD3A67B53C8" style="Mode=3;EOID=9E64E8D6;SOID=188D4BCE;Color=-1;LWidth=0;">
			<UML:ModelElement.taggedValue>
				<UML:TaggedValue tag="diagram_guid" value="EAID_45B6F2CD_C64B_4429_BA42_939006E4E759"/>
				<UML:TaggedValue tag="hidden" value="0"/>
			</UML:ModelElement.taggedValue>
		</UML:DiagramElement>
		<UML:DiagramElement geometry="SX=90;SY=-3;EX=-87;EY=-33;EDGE=2;$LLB=;LLT=;LMT=;LMB=;LRT=CX=81:CY=13:OX=44:OY=67:HDN=0:BLD=0:ITA=0:UND=0:CLR=-1:ALN=0:DIR=0:ROT=0;LRB=CX=18:CY=13:OX=-2:OY=-2:HDN=0:BLD=0:ITA=0:UND=0:CLR=-1:ALN=0:DIR=0:ROT=0;IRHS=;ILHS=;" subject="EAID_7E04BB82_EFD5_4457_85B3_6BD3A67B53C8" style="Mode=3;EOID=98C4AA5D;SOID=A2FE6E95;Color=-1;LWidth=0;">
			<UML:ModelElement.taggedValue>
				<UML:TaggedValue tag="diagram_guid" value="EAID_E5781FE1_9542_46bc_9B04_CEC52D6738FF"/>
				<UML:TaggedValue tag="hidden" value="0"/>
				<UML:TaggedValue tag="path" value="1022:-783;"/>
			</UML:ModelElement.taggedValue>
		</UML:DiagramElement>
		<UML:DiagramElement geometry="SX=0;SY=0;EX=0;EY=0;EDGE=1;$LLB=;LLT=;LMT=;LMB=;LRT=CX=81:CY=13:OX=-27:OY=25:HDN=0:BLD=0:ITA=0:UND=0:CLR=-1:ALN=0:DIR=0:ROT=0;LRB=CX=18:CY=13:OX=0:OY=0:HDN=0:BLD=0:ITA=0:UND=0:CLR=-1:ALN=0:DIR=0:ROT=0;IRHS=;ILHS=;" subject="EAID_7E04BB82_EFD5_4457_85B3_6BD3A67B53C8" style="Mode=3;EOID=92E5325F;SOID=0FC7484C;Color=-1;LWidth=0;">
			<UML:ModelElement.taggedValue>
				<UML:TaggedValue tag="diagram_guid" value="EAID_7B58CD34_CED0_47ea_9103_831EEC7B2C90"/>
				<UML:TaggedValue tag="hidden" value="0"/>
				<UML:TaggedValue tag="path" value="1120:-1080;1120:-960;1120:-840;1120:-720;1120:-620;1120:-560;1120:-500;"/>
			</UML:ModelElement.taggedValue>
		</UML:DiagramElement>
		<UML:DiagramElement geometry="EDGE=4;$LLB=;LLT=;LMT=;LMB=;LRT=CX=81:CY=13:OX=0:OY=0:HDN=0:BLD=0:ITA=0:UND=0:CLR=-1:ALN=0:DIR=0:ROT=0;LRB=CX=18:CY=13:OX=0:OY=0:HDN=0:BLD=0:ITA=0:UND=0:CLR=-1:ALN=0:DIR=0:ROT=0;IRHS=;ILHS=;" subject="EAID_7E04BB82_EFD5_4457_85B3_6BD3A67B53C8" style="Mode=1;EOID=268D421D;SOID=E5CCC2C0;Color=-1;LWidth=0;">
			<UML:ModelElement.taggedValue>
				<UML:TaggedValue tag="diagram_guid" value="EAID_6FCC5C53_037C_4e30_9CE2_1BE7F41DDF7A"/>
				<UML:TaggedValue tag="hidden" value="0"/>
			</UML:ModelElement.taggedValue>
		</UML:DiagramElement>
		<UML:DiagramElement geometry="EDGE=2;$LLB=;LLT=;LMT=;LMB=;LRT=CX=81:CY=13:OX=0:OY=0:HDN=0:BLD=0:ITA=0:UND=0:CLR=-1:ALN=0:DIR=0:ROT=0;LRB=CX=18:CY=13:OX=0:OY=0:HDN=0:BLD=0:ITA=0:UND=0:CLR=-1:ALN=0:DIR=0:ROT=0;IRHS=;ILHS=;" subject="EAID_7E04BB82_EFD5_4457_85B3_6BD3A67B53C8" style="Mode=3;EOID=91656806;SOID=B534C09B;Color=-1;LWidth=0;">
			<UML:ModelElement.taggedValue>
				<UML:TaggedValue tag="diagram_guid" value="EAID_19052557_1565_4d61_BC45_0CC382FFD0E5"/>
				<UML:TaggedValue tag="hidden" value="0"/>
			</UML:ModelElement.taggedValue>
		</UML:DiagramElement>
		<UML:DiagramElement geometry="EDGE=2;SX=0;SY=18;EX=0;EY=7;$LLB=;LLT=;LMT=;LMB=;LRT=CX=81:CY=13:OX=-4:OY=5:HDN=0:BLD=0:ITA=0:UND=0:CLR=-1:ALN=0:DIR=0:ROT=0;LRB=CX=18:CY=13:OX=-13:OY=-3:HDN=0:BLD=0:ITA=0:UND=0:CLR=-1:ALN=0:DIR=0:ROT=0;IRHS=;ILHS=;" subject="EAID_7E04BB82_EFD5_4457_85B3_6BD3A67B53C8" style="Mode=3;EOID=E63B968E;SOID=B760A378;Color=-1;LWidth=0;">
			<UML:ModelElement.taggedValue>
				<UML:TaggedValue tag="diagram_guid" value="EAID_D8FDBF75_7FD2_4679_890C_16F3A6F9C752"/>
				<UML:TaggedValue tag="hidden" value="0"/>
			</UML:ModelElement.taggedValue>
		</UML:DiagramElement>
		<UML:DiagramElement geometry="SX=65;SY=-15;EX=55;EY=-35;EDGE=1;$LLB=;LLT=;LMT=;LMB=;LRT=;LRB=;IRHS=;ILHS=;" subject="EAID_AE0E9EED_29A8_4ae8_98A2_05401A7F956B" style="Mode=3;EOID=9B7F3B21;SOID=16ED36EB;Color=-1;LWidth=0;">
			<UML:ModelElement.taggedValue>
				<UML:TaggedValue tag="diagram_guid" value="EAID_FF497341_D4FB_4ad0_8507_852367B8C95E"/>
				<UML:TaggedValue tag="hidden" value="0"/>
			</UML:ModelElement.taggedValue>
		</UML:DiagramElement>
		<UML:DiagramElement geometry="EDGE=1;$LLB=;LLT=;LMT=;LMB=;LRT=;LRB=;IRHS=;ILHS=;" subject="EAID_AE0E9EED_29A8_4ae8_98A2_05401A7F956B" style="Mode=3;EOID=46737D46;SOID=B760A378;Color=-1;LWidth=0;">
			<UML:ModelElement.taggedValue>
				<UML:TaggedValue tag="diagram_guid" value="EAID_D8FDBF75_7FD2_4679_890C_16F3A6F9C752"/>
				<UML:TaggedValue tag="hidden" value="0"/>
			</UML:ModelElement.taggedValue>
		</UML:DiagramElement>
		<UML:DiagramElement geometry="EDGE=1;$LLB=;LLT=;LMT=;LMB=CX=42:CY=13:OX=0:OY=0:HDN=1:BLD=0:ITA=0:UND=0:CLR=-1:ALN=0:DIR=0:ROT=0;LRT=;LRB=;IRHS=;ILHS=;" subject="EAID_D0B04AE8_6F20_4e32_95C0_4F08DB3629B8" style="Mode=3;EOID=0C924149;SOID=AA6D50BB;Color=-1;LWidth=0;">
			<UML:ModelElement.taggedValue>
				<UML:TaggedValue tag="diagram_guid" value="EAID_D3E59732_F8FF_4ce6_A182_9AE552B54588"/>
				<UML:TaggedValue tag="hidden" value="0"/>
			</UML:ModelElement.taggedValue>
		</UML:DiagramElement>
		<UML:DiagramElement geometry="EDGE=1;$LLB=;LLT=;LMT=;LMB=CX=42:CY=13:OX=0:OY=0:HDN=0:BLD=0:ITA=0:UND=0:CLR=-1:ALN=0:DIR=0:ROT=0;LRT=;LRB=;IRHS=;ILHS=;" subject="EAID_D0B04AE8_6F20_4e32_95C0_4F08DB3629B8" style="Mode=3;EOID=5A163F18;SOID=525E738D;Color=-1;LWidth=0;">
			<UML:ModelElement.taggedValue>
				<UML:TaggedValue tag="diagram_guid" value="EAID_83ED3DD9_9203_4a12_9064_0E2F7B0D1B03"/>
				<UML:TaggedValue tag="hidden" value="0"/>
			</UML:ModelElement.taggedValue>
		</UML:DiagramElement>
		<UML:DiagramElement geometry="SX=0;SY=0;EX=0;EY=0;EDGE=1;$LLB=;LLT=;LMT=;LMB=CX=42:CY=13:OX=0:OY=0:HDN=1:BLD=0:ITA=0:UND=0:CLR=-1:ALN=0:DIR=0:ROT=0;LRT=;LRB=;IRHS=;ILHS=;" subject="EAID_4970ADCE_2D31_4f74_B7F2_9B4858AFD08B" style="Mode=3;EOID=AA6D50BB;SOID=497CF274;Color=-1;LWidth=0;">
			<UML:ModelElement.taggedValue>
				<UML:TaggedValue tag="diagram_guid" value="EAID_D3E59732_F8FF_4ce6_A182_9AE552B54588"/>
				<UML:TaggedValue tag="hidden" value="0"/>
			</UML:ModelElement.taggedValue>
		</UML:DiagramElement>
	</XMI.content>
	<XMI.difference/>
	<XMI.extensions xmi.extender="Enterprise Architect 2.5">
		<EAStub xmi.id="EAID_50BFCF9E_F639_4b92_999F_99D1B94B7A45" name="HY_HydroNetwork" UMLType="Class"/>
		<EAModel.paramSub/>
		<EAStub xmi.id="EAID_CBE94F0D_9CA6_4cc3_9730_F0F7F31C2EB4" name="HY_HydroLocation" UMLType="Class"/>
		<EAStub xmi.id="EAID_A8ACD296_95A0_45f6_961E_4C92E4A95944" name="HY_HydroFeature" UMLType="Class"/>
		<EAStub xmi.id="EAPK_D5463997_E01A_47ff_B150_AB5F2622456C" name="HY_HydroFeature" UMLType="Package"/>
		<EAStub xmi.id="EAPK_D539B586_0ADB_4882_A8B9_AD6F1E2E34B7" name="HY_Features_Hydrology_Model" UMLType="Package"/>
	</XMI.extensions>
</XMI>
